{
  "success": true,
  "timestamp": "2025-10-26T13:02:19.036Z",
  "count": 248,
  "data": [
    {
      "symbol": "BTC",
      "name": "Bitcoin",
      "id": "bitcoin",
      "current_price": 113592.1071,
      "price_change_percentage_24h": 1.52419,
      "market_cap_rank": 1
    },
    {
      "symbol": "ETH",
      "name": "Ethereum",
      "id": "ethereum",
      "current_price": 4075.6748,
      "price_change_percentage_24h": 3.07663,
      "market_cap_rank": 2
    },
    {
      "symbol": "USDT",
      "name": "Tether",
      "id": "tether",
      "current_price": 1.0002,
      "price_change_percentage_24h": -0.01927,
      "market_cap_rank": 3
    },
    {
      "symbol": "XRP",
      "name": "XRP",
      "id": "ripple",
      "current_price": 2.6403,
      "price_change_percentage_24h": 2.32333,
      "market_cap_rank": 4
    },
    {
      "symbol": "BNB",
      "name": "BNB",
      "id": "binancecoin",
      "current_price": 1138.4634,
      "price_change_percentage_24h": 1.99917,
      "market_cap_rank": 5
    },
    {
      "symbol": "SOL",
      "name": "Solana",
      "id": "solana",
      "current_price": 197.9852,
      "price_change_percentage_24h": 2.12659,
      "market_cap_rank": 6
    },
    {
      "symbol": "USDC",
      "name": "USDC",
      "id": "usd-coin",
      "current_price": 0.9998,
      "price_change_percentage_24h": -0.00533,
      "market_cap_rank": 7
    },
    {
      "symbol": "DOGE",
      "name": "Dogecoin",
      "id": "dogecoin",
      "current_price": 0.2025,
      "price_change_percentage_24h": 2.18972,
      "market_cap_rank": 8
    },
    {
      "symbol": "TRX",
      "name": "TRON",
      "id": "tron",
      "current_price": 0.3003,
      "price_change_percentage_24h": 0.60042,
      "market_cap_rank": 9
    },
    {
      "symbol": "ADA",
      "name": "Cardano",
      "id": "cardano",
      "current_price": 0.6763,
      "price_change_percentage_24h": 3.22009,
      "market_cap_rank": 10
    },
    {
      "symbol": "WSTETH",
      "name": "Wrapped stETH",
      "id": "wrapped-steth",
      "current_price": 4958.4193,
      "price_change_percentage_24h": 3.09523,
      "market_cap_rank": 11
    },
    {
      "symbol": "WBTC",
      "name": "Wrapped Bitcoin",
      "id": "wrapped-bitcoin",
      "current_price": 113585.1585,
      "price_change_percentage_24h": 1.59352,
      "market_cap_rank": 12
    },
    {
      "symbol": "WBETH",
      "name": "Wrapped Beacon ETH",
      "id": "wrapped-beacon-eth",
      "current_price": 4396.8713,
      "price_change_percentage_24h": 3.11272,
      "market_cap_rank": 13
    },
    {
      "symbol": "FIGR_HELOC",
      "name": "Figure Heloc",
      "id": "figure-heloc",
      "current_price": 1,
      "price_change_percentage_24h": 101.09464,
      "market_cap_rank": 14
    },
    {
      "symbol": "HYPE",
      "name": "Hyperliquid",
      "id": "hyperliquid",
      "current_price": 47.7097,
      "price_change_percentage_24h": 15.39119,
      "market_cap_rank": 15
    },
    {
      "symbol": "LINK",
      "name": "Chainlink",
      "id": "chainlink",
      "current_price": 18.3393,
      "price_change_percentage_24h": 1.66855,
      "market_cap_rank": 16
    },
    {
      "symbol": "BCH",
      "name": "Bitcoin Cash",
      "id": "bitcoin-cash",
      "current_price": 561.8843,
      "price_change_percentage_24h": 10.95934,
      "market_cap_rank": 17
    },
    {
      "symbol": "WEETH",
      "name": "Wrapped eETH",
      "id": "wrapped-eeth",
      "current_price": 4395.9739,
      "price_change_percentage_24h": 3.11184,
      "market_cap_rank": 18
    },
    {
      "symbol": "XLM",
      "name": "Stellar",
      "id": "stellar",
      "current_price": 0.3317,
      "price_change_percentage_24h": 2.67526,
      "market_cap_rank": 19
    },
    {
      "symbol": "USDE",
      "name": "Ethena USDe",
      "id": "ethena-usde",
      "current_price": 0.9995,
      "price_change_percentage_24h": 0.01203,
      "market_cap_rank": 20
    },
    {
      "symbol": "SUI",
      "name": "Sui",
      "id": "sui",
      "current_price": 2.6166,
      "price_change_percentage_24h": 4.50388,
      "market_cap_rank": 21
    },
    {
      "symbol": "USDS",
      "name": "USDS",
      "id": "usds",
      "current_price": 0.9999,
      "price_change_percentage_24h": -0.02707,
      "market_cap_rank": 22
    },
    {
      "symbol": "BSC-USD",
      "name": "Binance Bridged USDT (BNB Smart Chain)",
      "id": "binance-bridged-usdt-bnb-smart-chain",
      "current_price": 1.0007,
      "price_change_percentage_24h": 0.07656,
      "market_cap_rank": 23
    },
    {
      "symbol": "AVAX",
      "name": "Avalanche",
      "id": "avalanche-2",
      "current_price": 20.3534,
      "price_change_percentage_24h": 4.18122,
      "market_cap_rank": 24
    },
    {
      "symbol": "LEO",
      "name": "LEO Token",
      "id": "leo-token",
      "current_price": 8.9837,
      "price_change_percentage_24h": -0.21477,
      "market_cap_rank": 25
    },
    {
      "symbol": "CBBTC",
      "name": "Coinbase Wrapped BTC",
      "id": "coinbase-wrapped-btc",
      "current_price": 113537.572,
      "price_change_percentage_24h": 1.54498,
      "market_cap_rank": 26
    },
    {
      "symbol": "HBAR",
      "name": "Hedera",
      "id": "hedera-hashgraph",
      "current_price": 0.1791,
      "price_change_percentage_24h": 5.01365,
      "market_cap_rank": 27
    },
    {
      "symbol": "LTC",
      "name": "Litecoin",
      "id": "litecoin",
      "current_price": 99.5089,
      "price_change_percentage_24h": 3.30527,
      "market_cap_rank": 28
    },
    {
      "symbol": "USDT0",
      "name": "USDT0",
      "id": "usdt0",
      "current_price": 1.0005,
      "price_change_percentage_24h": 0.01367,
      "market_cap_rank": 29
    },
    {
      "symbol": "XMR",
      "name": "Monero",
      "id": "monero",
      "current_price": 342.9139,
      "price_change_percentage_24h": 3.32817,
      "market_cap_rank": 30
    },
    {
      "symbol": "WBT",
      "name": "WhiteBIT Coin",
      "id": "whitebit",
      "current_price": 43.1112,
      "price_change_percentage_24h": 1.17849,
      "market_cap_rank": 31
    },
    {
      "symbol": "SHIB",
      "name": "Shiba Inu",
      "id": "shiba-inu",
      "current_price": 0,
      "price_change_percentage_24h": 2.98835,
      "market_cap_rank": 32
    },
    {
      "symbol": "MNT",
      "name": "Mantle",
      "id": "mantle",
      "current_price": 1.7838,
      "price_change_percentage_24h": 8.06984,
      "market_cap_rank": 33
    },
    {
      "symbol": "CRO",
      "name": "Cronos",
      "id": "crypto-com-chain",
      "current_price": 0.1534,
      "price_change_percentage_24h": 0.84554,
      "market_cap_rank": 34
    },
    {
      "symbol": "TON",
      "name": "Toncoin",
      "id": "the-open-network",
      "current_price": 2.1918,
      "price_change_percentage_24h": 2.0556,
      "market_cap_rank": 35
    },
    {
      "symbol": "ZEC",
      "name": "Zcash",
      "id": "zcash",
      "current_price": 324.3952,
      "price_change_percentage_24h": 18.43947,
      "market_cap_rank": 36
    },
    {
      "symbol": "SUSDE",
      "name": "Ethena Staked USDe",
      "id": "ethena-staked-usde",
      "current_price": 1.1991,
      "price_change_percentage_24h": -0.26049,
      "market_cap_rank": 37
    },
    {
      "symbol": "DOT",
      "name": "Polkadot",
      "id": "polkadot",
      "current_price": 3.1564,
      "price_change_percentage_24h": 3.07197,
      "market_cap_rank": 38
    },
    {
      "symbol": "DAI",
      "name": "Dai",
      "id": "dai",
      "current_price": 0.9986,
      "price_change_percentage_24h": -0.07842,
      "market_cap_rank": 39
    },
    {
      "symbol": "WLFI",
      "name": "World Liberty Financial",
      "id": "world-liberty-financial",
      "current_price": 0.1475,
      "price_change_percentage_24h": 10.25526,
      "market_cap_rank": 40
    },
    {
      "symbol": "TAO",
      "name": "Bittensor",
      "id": "bittensor",
      "current_price": 416.185,
      "price_change_percentage_24h": 6.63079,
      "market_cap_rank": 41
    },
    {
      "symbol": "UNI",
      "name": "Uniswap",
      "id": "uniswap",
      "current_price": 6.4636,
      "price_change_percentage_24h": 4.21781,
      "market_cap_rank": 42
    },
    {
      "symbol": "M",
      "name": "MemeCore",
      "id": "memecore",
      "current_price": 2.2208,
      "price_change_percentage_24h": -4.53202,
      "market_cap_rank": 43
    },
    {
      "symbol": "AAVE",
      "name": "Aave",
      "id": "aave",
      "current_price": 235.5995,
      "price_change_percentage_24h": 3.29278,
      "market_cap_rank": 44
    },
    {
      "symbol": "OKB",
      "name": "OKB",
      "id": "okb",
      "current_price": 168.9531,
      "price_change_percentage_24h": 1.56276,
      "market_cap_rank": 45
    },
    {
      "symbol": "ENA",
      "name": "Ethena",
      "id": "ethena",
      "current_price": 0.4878,
      "price_change_percentage_24h": 5.09627,
      "market_cap_rank": 46
    },
    {
      "symbol": "SUSDS",
      "name": "sUSDS",
      "id": "susds",
      "current_price": 1.0723,
      "price_change_percentage_24h": -0.15466,
      "market_cap_rank": 47
    },
    {
      "symbol": "BGB",
      "name": "Bitget Token",
      "id": "bitget-token",
      "current_price": 4.7468,
      "price_change_percentage_24h": 1.24864,
      "market_cap_rank": 48
    },
    {
      "symbol": "PEPE",
      "name": "Pepe",
      "id": "pepe",
      "current_price": 0,
      "price_change_percentage_24h": 2.67383,
      "market_cap_rank": 49
    },
    {
      "symbol": "NEAR",
      "name": "NEAR Protocol",
      "id": "near",
      "current_price": 2.3514,
      "price_change_percentage_24h": 3.72584,
      "market_cap_rank": 50
    },
    {
      "symbol": "USD1",
      "name": "USD1",
      "id": "usd1-wlfi",
      "current_price": 1.0005,
      "price_change_percentage_24h": 0.05102,
      "market_cap_rank": 51
    },
    {
      "symbol": "BUIDL",
      "name": "BlackRock USD Institutional Digital Liquidity Fund",
      "id": "blackrock-usd-institutional-digital-liquidity-fund",
      "current_price": 1,
      "price_change_percentage_24h": 0,
      "market_cap_rank": 52
    },
    {
      "symbol": "JITOSOL",
      "name": "Jito Staked SOL",
      "id": "jito-staked-sol",
      "current_price": 245.1338,
      "price_change_percentage_24h": 2.03853,
      "market_cap_rank": 53
    },
    {
      "symbol": "PYUSD",
      "name": "PayPal USD",
      "id": "paypal-usd",
      "current_price": 1,
      "price_change_percentage_24h": -0.00546,
      "market_cap_rank": 54
    },
    {
      "symbol": "ETC",
      "name": "Ethereum Classic",
      "id": "ethereum-classic",
      "current_price": 16.6054,
      "price_change_percentage_24h": 4.0864,
      "market_cap_rank": 55
    },
    {
      "symbol": "SOL",
      "name": "Wrapped SOL",
      "id": "wrapped-solana",
      "current_price": 197.8752,
      "price_change_percentage_24h": 2.0658,
      "market_cap_rank": 56
    },
    {
      "symbol": "APT",
      "name": "Aptos",
      "id": "aptos",
      "current_price": 3.5005,
      "price_change_percentage_24h": 5.88704,
      "market_cap_rank": 57
    },
    {
      "symbol": "WETH",
      "name": "Binance-Peg WETH",
      "id": "binance-peg-weth",
      "current_price": 4074.4758,
      "price_change_percentage_24h": 3.1383,
      "market_cap_rank": 58
    },
    {
      "symbol": "ASTER",
      "name": "Aster",
      "id": "aster-2",
      "current_price": 1.1956,
      "price_change_percentage_24h": 7.9176,
      "market_cap_rank": 59
    },
    {
      "symbol": "ONDO",
      "name": "Ondo",
      "id": "ondo-finance",
      "current_price": 0.7535,
      "price_change_percentage_24h": 3.31321,
      "market_cap_rank": 60
    },
    {
      "symbol": "JLP",
      "name": "Jupiter Perpetuals Liquidity Provider Token",
      "id": "jupiter-perpetuals-liquidity-provider-token",
      "current_price": 5.5776,
      "price_change_percentage_24h": 1.19691,
      "market_cap_rank": 61
    },
    {
      "symbol": "USDF",
      "name": "Falcon USD",
      "id": "falcon-finance",
      "current_price": 0.9989,
      "price_change_percentage_24h": 0.01576,
      "market_cap_rank": 62
    },
    {
      "symbol": "XAUT",
      "name": "Tether Gold",
      "id": "tether-gold",
      "current_price": 4107.3931,
      "price_change_percentage_24h": -0.31085,
      "market_cap_rank": 63
    },
    {
      "symbol": "POL",
      "name": "POL (ex-MATIC)",
      "id": "polygon-ecosystem-token",
      "current_price": 0.2002,
      "price_change_percentage_24h": 2.93991,
      "market_cap_rank": 64
    },
    {
      "symbol": "WLD",
      "name": "Worldcoin",
      "id": "worldcoin-wld",
      "current_price": 0.9335,
      "price_change_percentage_24h": 6.3072,
      "market_cap_rank": 65
    },
    {
      "symbol": "USDTB",
      "name": "USDtb",
      "id": "usdtb",
      "current_price": 0.9992,
      "price_change_percentage_24h": -0.08541,
      "market_cap_rank": 66
    },
    {
      "symbol": "GT",
      "name": "Gate",
      "id": "gatechain-token",
      "current_price": 15.5889,
      "price_change_percentage_24h": 0.56361,
      "market_cap_rank": 67
    },
    {
      "symbol": "RETH",
      "name": "Rocket Pool ETH",
      "id": "rocket-pool-eth",
      "current_price": 4662.3861,
      "price_change_percentage_24h": 3.09201,
      "market_cap_rank": 68
    },
    {
      "symbol": "ARB",
      "name": "Arbitrum",
      "id": "arbitrum",
      "current_price": 0.3291,
      "price_change_percentage_24h": 2.8694,
      "market_cap_rank": 69
    },
    {
      "symbol": "KCS",
      "name": "KuCoin",
      "id": "kucoin-shares",
      "current_price": 13.6545,
      "price_change_percentage_24h": 3.09565,
      "market_cap_rank": 70
    },
    {
      "symbol": "KHYPE",
      "name": "Kinetiq Staked HYPE",
      "id": "kinetic-staked-hype",
      "current_price": 47.8271,
      "price_change_percentage_24h": 15.1981,
      "market_cap_rank": 71
    },
    {
      "symbol": "HTX",
      "name": "HTX DAO",
      "id": "htx-dao",
      "current_price": 0,
      "price_change_percentage_24h": 0.68689,
      "market_cap_rank": 72
    },
    {
      "symbol": "PI",
      "name": "Pi Network",
      "id": "pi-network",
      "current_price": 0.2107,
      "price_change_percentage_24h": 1.6388,
      "market_cap_rank": 73
    },
    {
      "symbol": "ICP",
      "name": "Internet Computer",
      "id": "internet-computer",
      "current_price": 3.2292,
      "price_change_percentage_24h": 3.18997,
      "market_cap_rank": 74
    },
    {
      "symbol": "BNSOL",
      "name": "Binance Staked SOL",
      "id": "binance-staked-sol",
      "current_price": 213.8454,
      "price_change_percentage_24h": 2.14078,
      "market_cap_rank": 75
    },
    {
      "symbol": "HASH",
      "name": "Provenance Blockchain",
      "id": "hash-2",
      "current_price": 0.0344,
      "price_change_percentage_24h": 2.25245,
      "market_cap_rank": 76
    },
    {
      "symbol": "IP",
      "name": "Story",
      "id": "story-2",
      "current_price": 5.3299,
      "price_change_percentage_24h": 2.21107,
      "market_cap_rank": 77
    },
    {
      "symbol": "ALGO",
      "name": "Algorand",
      "id": "algorand",
      "current_price": 0.1894,
      "price_change_percentage_24h": 2.82531,
      "market_cap_rank": 78
    },
    {
      "symbol": "PUMP",
      "name": "Pump.fun",
      "id": "pump-fun",
      "current_price": 0.0046,
      "price_change_percentage_24h": 12.28874,
      "market_cap_rank": 79
    },
    {
      "symbol": "RSETH",
      "name": "Kelp DAO Restaked ETH",
      "id": "kelp-dao-restaked-eth",
      "current_price": 4303.2867,
      "price_change_percentage_24h": 2.96695,
      "market_cap_rank": 80
    },
    {
      "symbol": "KAS",
      "name": "Kaspa",
      "id": "kaspa",
      "current_price": 0.0589,
      "price_change_percentage_24h": 7.4188,
      "market_cap_rank": 81
    },
    {
      "symbol": "OSETH",
      "name": "StakeWise Staked ETH",
      "id": "stakewise-v3-oseth",
      "current_price": 4298.6958,
      "price_change_percentage_24h": 3.10841,
      "market_cap_rank": 82
    },
    {
      "symbol": "ATOM",
      "name": "Cosmos Hub",
      "id": "cosmos",
      "current_price": 3.2213,
      "price_change_percentage_24h": 2.02224,
      "market_cap_rank": 83
    },
    {
      "symbol": "VET",
      "name": "VeChain",
      "id": "vechain",
      "current_price": 0.0178,
      "price_change_percentage_24h": 2.76385,
      "market_cap_rank": 84
    },
    {
      "symbol": "WBNB",
      "name": "Wrapped BNB",
      "id": "wbnb",
      "current_price": 1138.9246,
      "price_change_percentage_24h": 1.96211,
      "market_cap_rank": 85
    },
    {
      "symbol": "LSETH",
      "name": "Liquid Staked ETH",
      "id": "liquid-staked-ethereum",
      "current_price": 4310.6012,
      "price_change_percentage_24h": 2.52576,
      "market_cap_rank": 86
    },
    {
      "symbol": "PENGU",
      "name": "Pudgy Penguins",
      "id": "pudgy-penguins",
      "current_price": 0.0221,
      "price_change_percentage_24h": 4.62113,
      "market_cap_rank": 87
    },
    {
      "symbol": "SKY",
      "name": "Sky",
      "id": "sky",
      "current_price": 0.0586,
      "price_change_percentage_24h": 1.07481,
      "market_cap_rank": 88
    },
    {
      "symbol": "JUP",
      "name": "Jupiter",
      "id": "jupiter-exchange-solana",
      "current_price": 0.4304,
      "price_change_percentage_24h": 7.42783,
      "market_cap_rank": 89
    },
    {
      "symbol": "PAXG",
      "name": "PAX Gold",
      "id": "pax-gold",
      "current_price": 4101.75,
      "price_change_percentage_24h": -0.22081,
      "market_cap_rank": 90
    },
    {
      "symbol": "LBTC",
      "name": "Lombard Staked BTC",
      "id": "lombard-staked-btc",
      "current_price": 113792.2654,
      "price_change_percentage_24h": 1.7814,
      "market_cap_rank": 91
    },
    {
      "symbol": "FLR",
      "name": "Flare",
      "id": "flare-networks",
      "current_price": 0.0174,
      "price_change_percentage_24h": 0.45869,
      "market_cap_rank": 92
    },
    {
      "symbol": "RENDER",
      "name": "Render",
      "id": "render-token",
      "current_price": 2.554,
      "price_change_percentage_24h": 4.27376,
      "market_cap_rank": 93
    },
    {
      "symbol": "BFUSD",
      "name": "BFUSD",
      "id": "bfusd",
      "current_price": 0.9999,
      "price_change_percentage_24h": -0.01018,
      "market_cap_rank": 94
    },
    {
      "symbol": "SYRUPUSDC",
      "name": "Syrup USDC",
      "id": "syrupusdc",
      "current_price": 1.1328,
      "price_change_percentage_24h": 0.01938,
      "market_cap_rank": 95
    },
    {
      "symbol": "EZETH",
      "name": "Renzo Restaked ETH",
      "id": "renzo-restaked-eth",
      "current_price": 4326.4379,
      "price_change_percentage_24h": 3.14523,
      "market_cap_rank": 96
    },
    {
      "symbol": "SEI",
      "name": "Sei",
      "id": "sei-network",
      "current_price": 0.2052,
      "price_change_percentage_24h": 4.14881,
      "market_cap_rank": 97
    },
    {
      "symbol": "COAI",
      "name": "ChainOpera AI",
      "id": "chainopera-ai",
      "current_price": 6.3174,
      "price_change_percentage_24h": -18.2675,
      "market_cap_rank": 98
    },
    {
      "symbol": "TRUMP",
      "name": "Official Trump",
      "id": "official-trump",
      "current_price": 6.1344,
      "price_change_percentage_24h": 2.9911,
      "market_cap_rank": 99
    },
    {
      "symbol": "QNT",
      "name": "Quant",
      "id": "quant-network",
      "current_price": 84.2919,
      "price_change_percentage_24h": 4.15726,
      "market_cap_rank": 100
    },
    {
      "symbol": "BONK",
      "name": "Bonk",
      "id": "bonk",
      "current_price": 0,
      "price_change_percentage_24h": 3.2063,
      "market_cap_rank": 101
    },
    {
      "symbol": "FIL",
      "name": "Filecoin",
      "id": "filecoin",
      "current_price": 1.6299,
      "price_change_percentage_24h": 4.699,
      "market_cap_rank": 102
    },
    {
      "symbol": "NEXO",
      "name": "NEXO",
      "id": "nexo",
      "current_price": 1.1411,
      "price_change_percentage_24h": 0.70335,
      "market_cap_rank": 103
    },
    {
      "symbol": "USDC",
      "name": "Binance Bridged USDC (BNB Smart Chain)",
      "id": "binance-bridged-usdc-bnb-smart-chain",
      "current_price": 1.0004,
      "price_change_percentage_24h": 0.0503,
      "market_cap_rank": 104
    },
    {
      "symbol": "SOLVBTC",
      "name": "Solv Protocol BTC",
      "id": "solv-btc",
      "current_price": 112579.6685,
      "price_change_percentage_24h": 0.7193,
      "market_cap_rank": 105
    },
    {
      "symbol": "XDC",
      "name": "XDC Network",
      "id": "xdce-crowd-sale",
      "current_price": 0.0623,
      "price_change_percentage_24h": -0.56707,
      "market_cap_rank": 106
    },
    {
      "symbol": "IMX",
      "name": "Immutable",
      "id": "immutable-x",
      "current_price": 0.556,
      "price_change_percentage_24h": 4.95219,
      "market_cap_rank": 107
    },
    {
      "symbol": "MORPHO",
      "name": "Morpho",
      "id": "morpho",
      "current_price": 2.0346,
      "price_change_percentage_24h": 1.06949,
      "market_cap_rank": 108
    },
    {
      "symbol": "SYRUPUSDT",
      "name": "syrupUSDT",
      "id": "syrupusdt",
      "current_price": 1.0995,
      "price_change_percentage_24h": 0.00675,
      "market_cap_rank": 109
    },
    {
      "symbol": "SPX",
      "name": "SPX6900",
      "id": "spx6900",
      "current_price": 1.1311,
      "price_change_percentage_24h": 11.0594,
      "market_cap_rank": 110
    },
    {
      "symbol": "METH",
      "name": "Mantle Staked Ether",
      "id": "mantle-staked-ether",
      "current_price": 4392.6105,
      "price_change_percentage_24h": 3.07663,
      "market_cap_rank": 111
    },
    {
      "symbol": "FDUSD",
      "name": "First Digital USD",
      "id": "first-digital-usd",
      "current_price": 0.9982,
      "price_change_percentage_24h": -0.10796,
      "market_cap_rank": 112
    },
    {
      "symbol": "JUPSOL",
      "name": "Jupiter Staked SOL",
      "id": "jupiter-staked-sol",
      "current_price": 226.8328,
      "price_change_percentage_24h": 2.08964,
      "market_cap_rank": 113
    },
    {
      "symbol": "USDG",
      "name": "Global Dollar",
      "id": "global-dollar",
      "current_price": 0.9999,
      "price_change_percentage_24h": -0.01997,
      "market_cap_rank": 114
    },
    {
      "symbol": "CAKE",
      "name": "PancakeSwap",
      "id": "pancakeswap-token",
      "current_price": 2.7982,
      "price_change_percentage_24h": 4.58312,
      "market_cap_rank": 115
    },
    {
      "symbol": "WBTC",
      "name": "Arbitrum Bridged WBTC (Arbitrum One)",
      "id": "arbitrum-bridged-wbtc-arbitrum-one",
      "current_price": 113647.3454,
      "price_change_percentage_24h": 1.70687,
      "market_cap_rank": 116
    },
    {
      "symbol": "RLUSD",
      "name": "Ripple USD",
      "id": "ripple-usd",
      "current_price": 1.0001,
      "price_change_percentage_24h": 0.0064,
      "market_cap_rank": 117
    },
    {
      "symbol": "TIA",
      "name": "Celestia",
      "id": "celestia",
      "current_price": 1.0616,
      "price_change_percentage_24h": 3.4951,
      "market_cap_rank": 118
    },
    {
      "symbol": "OP",
      "name": "Optimism",
      "id": "optimism",
      "current_price": 0.4602,
      "price_change_percentage_24h": 3.37954,
      "market_cap_rank": 119
    },
    {
      "symbol": "2Z",
      "name": "DoubleZero",
      "id": "doublezero",
      "current_price": 0.251,
      "price_change_percentage_24h": 6.66453,
      "market_cap_rank": 120
    },
    {
      "symbol": "CLBTC",
      "name": "clBTC",
      "id": "clbtc",
      "current_price": 111239.6024,
      "price_change_percentage_24h": null,
      "market_cap_rank": 121
    },
    {
      "symbol": "LDO",
      "name": "Lido DAO",
      "id": "lido-dao",
      "current_price": 0.958,
      "price_change_percentage_24h": 4.55702,
      "market_cap_rank": 122
    },
    {
      "symbol": "INJ",
      "name": "Injective",
      "id": "injective-protocol",
      "current_price": 8.7756,
      "price_change_percentage_24h": 3.57487,
      "market_cap_rank": 123
    },
    {
      "symbol": "STX",
      "name": "Stacks",
      "id": "blockstack",
      "current_price": 0.4675,
      "price_change_percentage_24h": 4.26677,
      "market_cap_rank": 124
    },
    {
      "symbol": "AERO",
      "name": "Aerodrome Finance",
      "id": "aerodrome-finance",
      "current_price": 0.9292,
      "price_change_percentage_24h": 9.88736,
      "market_cap_rank": 125
    },
    {
      "symbol": "MSOL",
      "name": "Marinade Staked SOL",
      "id": "msol",
      "current_price": 263.9804,
      "price_change_percentage_24h": 2.1822,
      "market_cap_rank": 126
    },
    {
      "symbol": "FTN",
      "name": "Fasttoken",
      "id": "fasttoken",
      "current_price": 2.0207,
      "price_change_percentage_24h": 7.5339,
      "market_cap_rank": 127
    },
    {
      "symbol": "VIRTUAL",
      "name": "Virtuals Protocol",
      "id": "virtual-protocol",
      "current_price": 1.2377,
      "price_change_percentage_24h": 0.80249,
      "market_cap_rank": 128
    },
    {
      "symbol": "CRV",
      "name": "Curve DAO",
      "id": "curve-dao-token",
      "current_price": 0.5578,
      "price_change_percentage_24h": 5.25871,
      "market_cap_rank": 129
    },
    {
      "symbol": "OUSG",
      "name": "OUSG",
      "id": "ousg",
      "current_price": 113.0583,
      "price_change_percentage_24h": 0,
      "market_cap_rank": 130
    },
    {
      "symbol": "USYC",
      "name": "Circle USYC",
      "id": "hashnote-usyc",
      "current_price": 1.1044,
      "price_change_percentage_24h": null,
      "market_cap_rank": 131
    },
    {
      "symbol": "XPL",
      "name": "Plasma",
      "id": "plasma",
      "current_price": 0.4035,
      "price_change_percentage_24h": 7.77975,
      "market_cap_rank": 132
    },
    {
      "symbol": "USTB",
      "name": "Superstate Short Duration U.S. Government Securities Fund (USTB)",
      "id": "superstate-short-duration-us-government-securities-fund-ustb",
      "current_price": 10.8679,
      "price_change_percentage_24h": 0,
      "market_cap_rank": 133
    },
    {
      "symbol": "FLOKI",
      "name": "FLOKI",
      "id": "floki",
      "current_price": 0.0001,
      "price_change_percentage_24h": 0.91933,
      "market_cap_rank": 134
    },
    {
      "symbol": "LIQUIDETH",
      "name": "Ether.Fi Liquid ETH",
      "id": "ether-fi-liquid-eth",
      "current_price": 4320.9914,
      "price_change_percentage_24h": 3.96245,
      "market_cap_rank": 135
    },
    {
      "symbol": "FET",
      "name": "Artificial Superintelligence Alliance",
      "id": "fetch-ai",
      "current_price": 0.2744,
      "price_change_percentage_24h": 6.19867,
      "market_cap_rank": 136
    },
    {
      "symbol": "WETH",
      "name": "L2 Standard Bridged WETH (Base)",
      "id": "l2-standard-bridged-weth-base",
      "current_price": 4069.2399,
      "price_change_percentage_24h": 3.06784,
      "market_cap_rank": 137
    },
    {
      "symbol": "GRT",
      "name": "The Graph",
      "id": "the-graph",
      "current_price": 0.0663,
      "price_change_percentage_24h": 3.40151,
      "market_cap_rank": 138
    },
    {
      "symbol": "USDX",
      "name": "Stables Labs USDX",
      "id": "usdx-money-usdx",
      "current_price": 0.9985,
      "price_change_percentage_24h": -0.01679,
      "market_cap_rank": 139
    },
    {
      "symbol": "USDY",
      "name": "Ondo US Dollar Yield",
      "id": "ondo-us-dollar-yield",
      "current_price": 1.0928,
      "price_change_percentage_24h": -0.14582,
      "market_cap_rank": 140
    },
    {
      "symbol": "PYTH",
      "name": "Pyth Network",
      "id": "pyth-network",
      "current_price": 0.1185,
      "price_change_percentage_24h": 2.76683,
      "market_cap_rank": 141
    },
    {
      "symbol": "TBTC",
      "name": "tBTC",
      "id": "tbtc",
      "current_price": 113465.6883,
      "price_change_percentage_24h": 1.62693,
      "market_cap_rank": 142
    },
    {
      "symbol": "XTZ",
      "name": "Tezos",
      "id": "tezos",
      "current_price": 0.6189,
      "price_change_percentage_24h": 2.52997,
      "market_cap_rank": 143
    },
    {
      "symbol": "S",
      "name": "Sonic",
      "id": "sonic-3",
      "current_price": 0.1714,
      "price_change_percentage_24h": 3.49402,
      "market_cap_rank": 144
    },
    {
      "symbol": "KAIA",
      "name": "Kaia",
      "id": "kaia",
      "current_price": 0.1102,
      "price_change_percentage_24h": 1.60899,
      "market_cap_rank": 145
    },
    {
      "symbol": "ETHX",
      "name": "Stader ETHx",
      "id": "stader-ethx",
      "current_price": 4367.4655,
      "price_change_percentage_24h": 3.11898,
      "market_cap_rank": 146
    },
    {
      "symbol": "GTETH",
      "name": "GTETH",
      "id": "gteth",
      "current_price": 4069.5718,
      "price_change_percentage_24h": 3.08243,
      "market_cap_rank": 147
    },
    {
      "symbol": "IOTA",
      "name": "IOTA",
      "id": "iota",
      "current_price": 0.15,
      "price_change_percentage_24h": 2.95377,
      "market_cap_rank": 148
    },
    {
      "symbol": "WETH",
      "name": "Arbitrum Bridged WETH (Arbitrum One)",
      "id": "arbitrum-bridged-weth-arbitrum-one",
      "current_price": 4072.3494,
      "price_change_percentage_24h": 3.05622,
      "market_cap_rank": 149
    },
    {
      "symbol": "ETHFI",
      "name": "Ether.fi",
      "id": "ether-fi",
      "current_price": 1.0824,
      "price_change_percentage_24h": 6.86746,
      "market_cap_rank": 150
    },
    {
      "symbol": "DASH",
      "name": "Dash",
      "id": "dash",
      "current_price": 48.1487,
      "price_change_percentage_24h": 16.32714,
      "market_cap_rank": 151
    },
    {
      "symbol": "BDX",
      "name": "Beldex",
      "id": "beldex",
      "current_price": 0.0792,
      "price_change_percentage_24h": 0.48453,
      "market_cap_rank": 152
    },
    {
      "symbol": "USDAI",
      "name": "USDai",
      "id": "usdai",
      "current_price": 1.0148,
      "price_change_percentage_24h": 0.04344,
      "market_cap_rank": 153
    },
    {
      "symbol": "CFX",
      "name": "Conflux",
      "id": "conflux-token",
      "current_price": 0.1138,
      "price_change_percentage_24h": 2.41008,
      "market_cap_rank": 154
    },
    {
      "symbol": "H",
      "name": "Humanity",
      "id": "humanity",
      "current_price": 0.3172,
      "price_change_percentage_24h": 2.03939,
      "market_cap_rank": 155
    },
    {
      "symbol": "AB",
      "name": "AB",
      "id": "newton-project",
      "current_price": 0.0069,
      "price_change_percentage_24h": -0.27425,
      "market_cap_rank": 156
    },
    {
      "symbol": "THETA",
      "name": "Theta Network",
      "id": "theta-token",
      "current_price": 0.5655,
      "price_change_percentage_24h": 3.77947,
      "market_cap_rank": 157
    },
    {
      "symbol": "PENDLE",
      "name": "Pendle",
      "id": "pendle",
      "current_price": 3.3387,
      "price_change_percentage_24h": 4.53211,
      "market_cap_rank": 158
    },
    {
      "symbol": "WIF",
      "name": "dogwifhat",
      "id": "dogwifcoin",
      "current_price": 0.56,
      "price_change_percentage_24h": 3.88573,
      "market_cap_rank": 159
    },
    {
      "symbol": "MYX",
      "name": "MYX Finance",
      "id": "myx-finance",
      "current_price": 2.9328,
      "price_change_percentage_24h": 0.62141,
      "market_cap_rank": 160
    },
    {
      "symbol": "CBETH",
      "name": "Coinbase Wrapped Staked ETH",
      "id": "coinbase-wrapped-staked-eth",
      "current_price": 4479.278,
      "price_change_percentage_24h": 3.00788,
      "market_cap_rank": 161
    },
    {
      "symbol": "DAI",
      "name": "Polygon PoS Bridged DAI (Polygon POS)",
      "id": "polygon-pos-bridged-dai-polygon-pos",
      "current_price": 0.9999,
      "price_change_percentage_24h": -0.00001,
      "market_cap_rank": 162
    },
    {
      "symbol": "USD0",
      "name": "Usual USD",
      "id": "usual-usd",
      "current_price": 0.9979,
      "price_change_percentage_24h": -0.02296,
      "market_cap_rank": 163
    },
    {
      "symbol": "USDC.E",
      "name": "Polygon Bridged USDC (Polygon PoS)",
      "id": "bridged-usdc-polygon-pos-bridge",
      "current_price": 0.9998,
      "price_change_percentage_24h": -0.0043,
      "market_cap_rank": 164
    },
    {
      "symbol": "SWETH",
      "name": "Swell Ethereum",
      "id": "sweth",
      "current_price": 4490.1535,
      "price_change_percentage_24h": 3.11085,
      "market_cap_rank": 165
    },
    {
      "symbol": "ENS",
      "name": "Ethereum Name Service",
      "id": "ethereum-name-service",
      "current_price": 16.3782,
      "price_change_percentage_24h": 5.69022,
      "market_cap_rank": 166
    },
    {
      "symbol": "STRK",
      "name": "Starknet",
      "id": "starknet",
      "current_price": 0.124,
      "price_change_percentage_24h": 3.38075,
      "market_cap_rank": 167
    },
    {
      "symbol": "SAND",
      "name": "The Sandbox",
      "id": "the-sandbox",
      "current_price": 0.2183,
      "price_change_percentage_24h": 2.77273,
      "market_cap_rank": 168
    },
    {
      "symbol": "BTC.B",
      "name": "Avalanche Bridged BTC (Avalanche)",
      "id": "bitcoin-avalanche-bridged-btc-b",
      "current_price": 113594.1892,
      "price_change_percentage_24h": 1.56008,
      "market_cap_rank": 169
    },
    {
      "symbol": "TWT",
      "name": "Trust Wallet",
      "id": "trust-wallet-token",
      "current_price": 1.269,
      "price_change_percentage_24h": -0.24059,
      "market_cap_rank": 170
    },
    {
      "symbol": "JASMY",
      "name": "JasmyCoin",
      "id": "jasmycoin",
      "current_price": 0.0109,
      "price_change_percentage_24h": 2.01863,
      "market_cap_rank": 171
    },
    {
      "symbol": "GALA",
      "name": "GALA",
      "id": "gala",
      "current_price": 0.0114,
      "price_change_percentage_24h": 1.98502,
      "market_cap_rank": 172
    },
    {
      "symbol": "BTT",
      "name": "BitTorrent",
      "id": "bittorrent",
      "current_price": 0,
      "price_change_percentage_24h": 5.3185,
      "market_cap_rank": 173
    },
    {
      "symbol": "DOGE",
      "name": "Binance-Peg Dogecoin",
      "id": "binance-peg-dogecoin",
      "current_price": 0.2027,
      "price_change_percentage_24h": 2.27413,
      "market_cap_rank": 174
    },
    {
      "symbol": "USDT",
      "name": "Mantle Bridged USDT (Mantle)",
      "id": "mantle-bridged-usdt-mantle",
      "current_price": 1.0034,
      "price_change_percentage_24h": 0.20823,
      "market_cap_rank": 175
    },
    {
      "symbol": "RAY",
      "name": "Raydium",
      "id": "raydium",
      "current_price": 1.8635,
      "price_change_percentage_24h": 5.63828,
      "market_cap_rank": 176
    },
    {
      "symbol": "BSV",
      "name": "Bitcoin SV",
      "id": "bitcoin-cash-sv",
      "current_price": 24.1109,
      "price_change_percentage_24h": 11.50551,
      "market_cap_rank": 177
    },
    {
      "symbol": "EETH",
      "name": "ether.fi Staked ETH",
      "id": "ether-fi-staked-eth",
      "current_price": 4068.1088,
      "price_change_percentage_24h": 3.01473,
      "market_cap_rank": 178
    },
    {
      "symbol": "TUSD",
      "name": "TrueUSD",
      "id": "true-usd",
      "current_price": 0.9972,
      "price_change_percentage_24h": -0.12153,
      "market_cap_rank": 179
    },
    {
      "symbol": "SAVAX",
      "name": "BENQI Liquid Staked AVAX",
      "id": "benqi-liquid-staked-avax",
      "current_price": 25.0134,
      "price_change_percentage_24h": 4.33609,
      "market_cap_rank": 180
    },
    {
      "symbol": "A",
      "name": "Vaulta",
      "id": "vaulta",
      "current_price": 0.2993,
      "price_change_percentage_24h": 2.22445,
      "market_cap_rank": 181
    },
    {
      "symbol": "STEAKUSDC",
      "name": "Steakhouse USDC Morpho Vault",
      "id": "steakhouse-usdc-morpho-vault",
      "current_price": 1.1054,
      "price_change_percentage_24h": 0.00856,
      "market_cap_rank": 182
    },
    {
      "symbol": "WEETH",
      "name": "Arbitrum Bridged Wrapped eETH (Arbitrum)",
      "id": "arbitrum-bridged-wrapped-eeth",
      "current_price": 4392.417,
      "price_change_percentage_24h": 3.01777,
      "market_cap_rank": 183
    },
    {
      "symbol": "MANA",
      "name": "Decentraland",
      "id": "decentraland",
      "current_price": 0.2462,
      "price_change_percentage_24h": 2.17374,
      "market_cap_rank": 184
    },
    {
      "symbol": "WHYPE",
      "name": "Wrapped HYPE",
      "id": "wrapped-hype",
      "current_price": 47.6347,
      "price_change_percentage_24h": 14.75866,
      "market_cap_rank": 185
    },
    {
      "symbol": "ASBNB",
      "name": "Aster Staked BNB",
      "id": "astherus-staked-bnb",
      "current_price": 1206.0357,
      "price_change_percentage_24h": 2.20656,
      "market_cap_rank": 186
    },
    {
      "symbol": "BORG",
      "name": "SwissBorg",
      "id": "swissborg",
      "current_price": 0.4686,
      "price_change_percentage_24h": -0.57275,
      "market_cap_rank": 187
    },
    {
      "symbol": "EIGEN",
      "name": "EigenCloud (prev. EigenLayer)",
      "id": "eigenlayer",
      "current_price": 1.1724,
      "price_change_percentage_24h": 7.86838,
      "market_cap_rank": 188
    },
    {
      "symbol": "USDD",
      "name": "USDD",
      "id": "usdd",
      "current_price": 0.9999,
      "price_change_percentage_24h": -0.03973,
      "market_cap_rank": 189
    },
    {
      "symbol": "CMETH",
      "name": "Mantle Restaked ETH",
      "id": "mantle-restaked-eth",
      "current_price": 4394.6462,
      "price_change_percentage_24h": 3.35207,
      "market_cap_rank": 190
    },
    {
      "symbol": "JTO",
      "name": "Jito",
      "id": "jito-governance-token",
      "current_price": 1.1494,
      "price_change_percentage_24h": 2.37886,
      "market_cap_rank": 191
    },
    {
      "symbol": "FLOW",
      "name": "Flow",
      "id": "flow",
      "current_price": 0.2794,
      "price_change_percentage_24h": 2.29704,
      "market_cap_rank": 192
    },
    {
      "symbol": "SYRUP",
      "name": "Maple Finance",
      "id": "syrup",
      "current_price": 0.4005,
      "price_change_percentage_24h": 4.47666,
      "market_cap_rank": 193
    },
    {
      "symbol": "WETH",
      "name": "Polygon PoS Bridged WETH (Polygon POS)",
      "id": "polygon-pos-bridged-weth-polygon-pos",
      "current_price": 4072.7582,
      "price_change_percentage_24h": 3.12884,
      "market_cap_rank": 194
    },
    {
      "symbol": "VKHYPE",
      "name": "Kinetiq Earn Vault",
      "id": "kinetiq-earn-vault",
      "current_price": 48.1381,
      "price_change_percentage_24h": 15.36721,
      "market_cap_rank": 195
    },
    {
      "symbol": "ATH",
      "name": "Aethir",
      "id": "aethir",
      "current_price": 0.0306,
      "price_change_percentage_24h": 5.21671,
      "market_cap_rank": 196
    },
    {
      "symbol": "SNX",
      "name": "Synthetix",
      "id": "havven",
      "current_price": 1.26,
      "price_change_percentage_24h": 0.96466,
      "market_cap_rank": 197
    },
    {
      "symbol": "SUN",
      "name": "Sun Token",
      "id": "sun-token",
      "current_price": 0.0226,
      "price_change_percentage_24h": 0.66334,
      "market_cap_rank": 198
    },
    {
      "symbol": "ZORA",
      "name": "Zora",
      "id": "zora",
      "current_price": 0.0949,
      "price_change_percentage_24h": 4.22038,
      "market_cap_rank": 199
    },
    {
      "symbol": "SATUSD",
      "name": "Satoshi Stablecoin",
      "id": "satoshi-stablecoin",
      "current_price": 1.0005,
      "price_change_percentage_24h": 0.58947,
      "market_cap_rank": 200
    },
    {
      "symbol": "FRXETH",
      "name": "Frax Ether",
      "id": "frax-ether",
      "current_price": 4041.1128,
      "price_change_percentage_24h": 3.17021,
      "market_cap_rank": 201
    },
    {
      "symbol": "MERL",
      "name": "Merlin Chain",
      "id": "merlin-chain",
      "current_price": 0.417,
      "price_change_percentage_24h": -1.66318,
      "market_cap_rank": 202
    },
    {
      "symbol": "GHO",
      "name": "GHO",
      "id": "gho",
      "current_price": 0.9996,
      "price_change_percentage_24h": 0.00696,
      "market_cap_rank": 203
    },
    {
      "symbol": "USDB",
      "name": "USDB",
      "id": "usdb",
      "current_price": 1.0028,
      "price_change_percentage_24h": 0.86012,
      "market_cap_rank": 204
    },
    {
      "symbol": "FARTCOIN",
      "name": "Fartcoin",
      "id": "fartcoin",
      "current_price": 0.4068,
      "price_change_percentage_24h": 6.11616,
      "market_cap_rank": 205
    },
    {
      "symbol": "APE",
      "name": "ApeCoin",
      "id": "apecoin",
      "current_price": 0.443,
      "price_change_percentage_24h": -1.14001,
      "market_cap_rank": 206
    },
    {
      "symbol": "NFT",
      "name": "AINFT",
      "id": "apenft",
      "current_price": 0,
      "price_change_percentage_24h": -0.67255,
      "market_cap_rank": 207
    },
    {
      "symbol": "VSN",
      "name": "Vision",
      "id": "vision-3",
      "current_price": 0.1183,
      "price_change_percentage_24h": 0.75354,
      "market_cap_rank": 208
    },
    {
      "symbol": "AIC",
      "name": "AI Companions",
      "id": "ai-companions",
      "current_price": 0.3972,
      "price_change_percentage_24h": -0.49658,
      "market_cap_rank": 209
    },
    {
      "symbol": "TRAC",
      "name": "OriginTrail",
      "id": "origintrail",
      "current_price": 0.7919,
      "price_change_percentage_24h": -2.10608,
      "market_cap_rank": 210
    },
    {
      "symbol": "ZBCN",
      "name": "Zebec Network",
      "id": "zebec-network",
      "current_price": 0.0041,
      "price_change_percentage_24h": 4.357,
      "market_cap_rank": 211
    },
    {
      "symbol": "FF",
      "name": "Falcon Finance",
      "id": "falcon-finance-ff",
      "current_price": 0.165,
      "price_change_percentage_24h": 0.65524,
      "market_cap_rank": 212
    },
    {
      "symbol": "DEXE",
      "name": "DeXe",
      "id": "dexe",
      "current_price": 6.7161,
      "price_change_percentage_24h": 2.5544,
      "market_cap_rank": 213
    },
    {
      "symbol": "HNT",
      "name": "Helium",
      "id": "helium",
      "current_price": 2.0357,
      "price_change_percentage_24h": 3.83177,
      "market_cap_rank": 214
    },
    {
      "symbol": "APEPE",
      "name": "Ape and Pepe",
      "id": "ape-and-pepe",
      "current_price": 0,
      "price_change_percentage_24h": 3.85705,
      "market_cap_rank": 215
    },
    {
      "symbol": "COMP",
      "name": "Compound",
      "id": "compound-governance-token",
      "current_price": 38.9263,
      "price_change_percentage_24h": 3.12933,
      "market_cap_rank": 216
    },
    {
      "symbol": "TEL",
      "name": "Telcoin",
      "id": "telcoin",
      "current_price": 0.004,
      "price_change_percentage_24h": 5.78717,
      "market_cap_rank": 217
    },
    {
      "symbol": "0G",
      "name": "0G",
      "id": "zero-gravity",
      "current_price": 1.7654,
      "price_change_percentage_24h": 3.81519,
      "market_cap_rank": 218
    },
    {
      "symbol": "NEO",
      "name": "NEO",
      "id": "neo",
      "current_price": 5.3142,
      "price_change_percentage_24h": 3.40391,
      "market_cap_rank": 219
    },
    {
      "symbol": "TIBBIR",
      "name": "Ribbita by Virtuals",
      "id": "ribbita-by-virtuals",
      "current_price": 0.3744,
      "price_change_percentage_24h": -0.90546,
      "market_cap_rank": 220
    },
    {
      "symbol": "OHM",
      "name": "Olympus",
      "id": "olympus",
      "current_price": 22.7783,
      "price_change_percentage_24h": 0.7857,
      "market_cap_rank": 221
    },
    {
      "symbol": "EUTBL",
      "name": "Spiko EU T-Bills Money Market Fund",
      "id": "eutbl",
      "current_price": 1.2086,
      "price_change_percentage_24h": -0.15646,
      "market_cap_rank": 222
    },
    {
      "symbol": "UBTC",
      "name": "Unit Bitcoin",
      "id": "unit-bitcoin",
      "current_price": 113604.6627,
      "price_change_percentage_24h": 1.52956,
      "market_cap_rank": 223
    },
    {
      "symbol": "SDAI",
      "name": "Savings Dai",
      "id": "savings-dai",
      "current_price": 1.1674,
      "price_change_percentage_24h": 0.04072,
      "market_cap_rank": 224
    },
    {
      "symbol": "ETH+",
      "name": "ETHPlus",
      "id": "reserve-protocol-eth-plus",
      "current_price": 4303.1481,
      "price_change_percentage_24h": 3.07314,
      "market_cap_rank": 225
    },
    {
      "symbol": "WAL",
      "name": "Walrus",
      "id": "walrus-2",
      "current_price": 0.2499,
      "price_change_percentage_24h": -0.15158,
      "market_cap_rank": 226
    },
    {
      "symbol": "SENA",
      "name": "Ethena Staked ENA",
      "id": "ethena-staked-ena",
      "current_price": 0.4811,
      "price_change_percentage_24h": 1.10695,
      "market_cap_rank": 227
    },
    {
      "symbol": "W",
      "name": "Wormhole",
      "id": "wormhole",
      "current_price": 0.0757,
      "price_change_percentage_24h": 3.60888,
      "market_cap_rank": 228
    },
    {
      "symbol": "FLUID",
      "name": "Fluid",
      "id": "instadapp",
      "current_price": 4.6899,
      "price_change_percentage_24h": 2.65645,
      "market_cap_rank": 229
    },
    {
      "symbol": "TETH",
      "name": "Treehouse ETH",
      "id": "treehouse-eth",
      "current_price": 4973.0015,
      "price_change_percentage_24h": 3.13654,
      "market_cap_rank": 230
    },
    {
      "symbol": "GNO",
      "name": "Gnosis",
      "id": "gnosis",
      "current_price": 136.8654,
      "price_change_percentage_24h": 5.08988,
      "market_cap_rank": 231
    },
    {
      "symbol": "SRUSD",
      "name": "Reservoir srUSD",
      "id": "reservoir-srusd",
      "current_price": 1.1062,
      "price_change_percentage_24h": -0.11696,
      "market_cap_rank": 232
    },
    {
      "symbol": "XEC",
      "name": "eCash",
      "id": "ecash",
      "current_price": 0,
      "price_change_percentage_24h": 17.86916,
      "market_cap_rank": 233
    },
    {
      "symbol": "LION",
      "name": "Loaded Lions",
      "id": "loaded-lions",
      "current_price": 0.0112,
      "price_change_percentage_24h": 1.3408,
      "market_cap_rank": 234
    },
    {
      "symbol": "RSR",
      "name": "Reserve Rights",
      "id": "reserve-rights-token",
      "current_price": 0.0057,
      "price_change_percentage_24h": 3.18508,
      "market_cap_rank": 235
    },
    {
      "symbol": "BBSOL",
      "name": "Bybit Staked SOL",
      "id": "bybit-staked-sol",
      "current_price": 220.7389,
      "price_change_percentage_24h": 2.29073,
      "market_cap_rank": 236
    },
    {
      "symbol": "DSOL",
      "name": "Drift Staked SOL",
      "id": "drift-staked-sol",
      "current_price": 227.589,
      "price_change_percentage_24h": 2.0605,
      "market_cap_rank": 237
    },
    {
      "symbol": "JST",
      "name": "JUST",
      "id": "just",
      "current_price": 0.0341,
      "price_change_percentage_24h": 2.42326,
      "market_cap_rank": 238
    },
    {
      "symbol": "ATONE",
      "name": "AtomOne",
      "id": "atomone",
      "current_price": 2.7586,
      "price_change_percentage_24h": -1.07578,
      "market_cap_rank": 239
    },
    {
      "symbol": "CHZ",
      "name": "Chiliz",
      "id": "chiliz",
      "current_price": 0.0334,
      "price_change_percentage_24h": 3.1298,
      "market_cap_rank": 240
    },
    {
      "symbol": "WETH",
      "name": "Mantle Bridged WETH (Mantle)",
      "id": "wrapped-ether-mantle-bridge",
      "current_price": 4086.9787,
      "price_change_percentage_24h": 3.25671,
      "market_cap_rank": 241
    },
    {
      "symbol": "WAVAX",
      "name": "Wrapped AVAX",
      "id": "wrapped-avax",
      "current_price": 20.3369,
      "price_change_percentage_24h": 4.11436,
      "market_cap_rank": 242
    },
    {
      "symbol": "TOSHI",
      "name": "Toshi",
      "id": "toshi",
      "current_price": 0.0008,
      "price_change_percentage_24h": 0.151,
      "market_cap_rank": 243
    },
    {
      "symbol": "XCN",
      "name": "Onyxcoin",
      "id": "chain-2",
      "current_price": 0.009,
      "price_change_percentage_24h": 1.14105,
      "market_cap_rank": 244
    },
    {
      "symbol": "WEMIX",
      "name": "WEMIX",
      "id": "wemix-token",
      "current_price": 0.7066,
      "price_change_percentage_24h": 7.36606,
      "market_cap_rank": 245
    },
    {
      "symbol": "XSOLVBTC",
      "name": "Solv Protocol Staked BTC",
      "id": "solv-protocol-solvbtc-bbn",
      "current_price": 111793.7282,
      "price_change_percentage_24h": 1.00992,
      "market_cap_rank": 246
    },
    {
      "symbol": "USELESS",
      "name": "Useless Coin",
      "id": "useless-3",
      "current_price": 0.3219,
      "price_change_percentage_24h": 7.38912,
      "market_cap_rank": 247
    },
    {
      "symbol": "CGETH.HASHKEY",
      "name": "cgETH Hashkey Cloud",
      "id": "cgeth-hashkey-cloud",
      "current_price": 1589.3594,
      "price_change_percentage_24h": -52.99604,
      "market_cap_rank": 248
    }
  ]
}