{
  "success": true,
  "timestamp": "2025-10-31T08:06:53.434Z",
  "count": 248,
  "data": [
    {
      "symbol": "BTC",
      "name": "Bitcoin",
      "id": "bitcoin",
      "current_price": 109657.0228,
      "price_change_percentage_24h": -1.44545,
      "market_cap_rank": 1
    },
    {
      "symbol": "ETH",
      "name": "Ethereum",
      "id": "ethereum",
      "current_price": 3835.7887,
      "price_change_percentage_24h": -2.50633,
      "market_cap_rank": 2
    },
    {
      "symbol": "USDT",
      "name": "Tether",
      "id": "tether",
      "current_price": 1,
      "price_change_percentage_24h": -0.02033,
      "market_cap_rank": 3
    },
    {
      "symbol": "BNB",
      "name": "BNB",
      "id": "binancecoin",
      "current_price": 1099.26,
      "price_change_percentage_24h": -1.59259,
      "market_cap_rank": 4
    },
    {
      "symbol": "XRP",
      "name": "XRP",
      "id": "ripple",
      "current_price": 2.4777,
      "price_change_percentage_24h": -4.08936,
      "market_cap_rank": 5
    },
    {
      "symbol": "SOL",
      "name": "Solana",
      "id": "solana",
      "current_price": 185.5099,
      "price_change_percentage_24h": -5.17512,
      "market_cap_rank": 6
    },
    {
      "symbol": "USDC",
      "name": "USDC",
      "id": "usd-coin",
      "current_price": 0.9997,
      "price_change_percentage_24h": -0.01512,
      "market_cap_rank": 7
    },
    {
      "symbol": "DOGE",
      "name": "Dogecoin",
      "id": "dogecoin",
      "current_price": 0.1846,
      "price_change_percentage_24h": -3.88088,
      "market_cap_rank": 8
    },
    {
      "symbol": "TRX",
      "name": "TRON",
      "id": "tron",
      "current_price": 0.295,
      "price_change_percentage_24h": -0.73312,
      "market_cap_rank": 9
    },
    {
      "symbol": "ADA",
      "name": "Cardano",
      "id": "cardano",
      "current_price": 0.6114,
      "price_change_percentage_24h": -5.08742,
      "market_cap_rank": 10
    },
    {
      "symbol": "WSTETH",
      "name": "Wrapped stETH",
      "id": "wrapped-steth",
      "current_price": 4669.6837,
      "price_change_percentage_24h": -2.57173,
      "market_cap_rank": 11
    },
    {
      "symbol": "WBTC",
      "name": "Wrapped Bitcoin",
      "id": "wrapped-bitcoin",
      "current_price": 109550.2391,
      "price_change_percentage_24h": -1.50352,
      "market_cap_rank": 12
    },
    {
      "symbol": "WBETH",
      "name": "Wrapped Beacon ETH",
      "id": "wrapped-beacon-eth",
      "current_price": 4147.6006,
      "price_change_percentage_24h": -2.48265,
      "market_cap_rank": 13
    },
    {
      "symbol": "LINK",
      "name": "Chainlink",
      "id": "chainlink",
      "current_price": 17.2351,
      "price_change_percentage_24h": -6.04124,
      "market_cap_rank": 14
    },
    {
      "symbol": "HYPE",
      "name": "Hyperliquid",
      "id": "hyperliquid",
      "current_price": 44.0566,
      "price_change_percentage_24h": -11.1075,
      "market_cap_rank": 15
    },
    {
      "symbol": "BCH",
      "name": "Bitcoin Cash",
      "id": "bitcoin-cash",
      "current_price": 556.0452,
      "price_change_percentage_24h": -2.8448,
      "market_cap_rank": 16
    },
    {
      "symbol": "WEETH",
      "name": "Wrapped eETH",
      "id": "wrapped-eeth",
      "current_price": 4138.1112,
      "price_change_percentage_24h": -2.69603,
      "market_cap_rank": 17
    },
    {
      "symbol": "XLM",
      "name": "Stellar",
      "id": "stellar",
      "current_price": 0.3016,
      "price_change_percentage_24h": -4.56832,
      "market_cap_rank": 18
    },
    {
      "symbol": "USDE",
      "name": "Ethena USDe",
      "id": "ethena-usde",
      "current_price": 0.9992,
      "price_change_percentage_24h": -0.03294,
      "market_cap_rank": 19
    },
    {
      "symbol": "USDS",
      "name": "USDS",
      "id": "usds",
      "current_price": 0.9997,
      "price_change_percentage_24h": -0.01174,
      "market_cap_rank": 20
    },
    {
      "symbol": "BSC-USD",
      "name": "Binance Bridged USDT (BNB Smart Chain)",
      "id": "binance-bridged-usdt-bnb-smart-chain",
      "current_price": 0.9998,
      "price_change_percentage_24h": -0.02416,
      "market_cap_rank": 21
    },
    {
      "symbol": "LEO",
      "name": "LEO Token",
      "id": "leo-token",
      "current_price": 9.608,
      "price_change_percentage_24h": -0.16543,
      "market_cap_rank": 22
    },
    {
      "symbol": "SUI",
      "name": "Sui",
      "id": "sui",
      "current_price": 2.3399,
      "price_change_percentage_24h": -6.58882,
      "market_cap_rank": 23
    },
    {
      "symbol": "HBAR",
      "name": "Hedera",
      "id": "hedera-hashgraph",
      "current_price": 0.1925,
      "price_change_percentage_24h": -7.3813,
      "market_cap_rank": 24
    },
    {
      "symbol": "AVAX",
      "name": "Avalanche",
      "id": "avalanche-2",
      "current_price": 18.2838,
      "price_change_percentage_24h": -7.8953,
      "market_cap_rank": 25
    },
    {
      "symbol": "CBBTC",
      "name": "Coinbase Wrapped BTC",
      "id": "coinbase-wrapped-btc",
      "current_price": 109555.6773,
      "price_change_percentage_24h": -1.55133,
      "market_cap_rank": 26
    },
    {
      "symbol": "LTC",
      "name": "Litecoin",
      "id": "litecoin",
      "current_price": 94.3195,
      "price_change_percentage_24h": -4.39544,
      "market_cap_rank": 27
    },
    {
      "symbol": "WBT",
      "name": "WhiteBIT Coin",
      "id": "whitebit",
      "current_price": 44.324,
      "price_change_percentage_24h": 5.03075,
      "market_cap_rank": 28
    },
    {
      "symbol": "ZEC",
      "name": "Zcash",
      "id": "zcash",
      "current_price": 386.9817,
      "price_change_percentage_24h": 7.64872,
      "market_cap_rank": 29
    },
    {
      "symbol": "XMR",
      "name": "Monero",
      "id": "monero",
      "current_price": 323.3321,
      "price_change_percentage_24h": -2.33992,
      "market_cap_rank": 30
    },
    {
      "symbol": "USDT0",
      "name": "USDT0",
      "id": "usdt0",
      "current_price": 1.0001,
      "price_change_percentage_24h": 0.00656,
      "market_cap_rank": 31
    },
    {
      "symbol": "SHIB",
      "name": "Shiba Inu",
      "id": "shiba-inu",
      "current_price": 0,
      "price_change_percentage_24h": -3.1167,
      "market_cap_rank": 32
    },
    {
      "symbol": "TON",
      "name": "Toncoin",
      "id": "the-open-network",
      "current_price": 2.1446,
      "price_change_percentage_24h": -2.82728,
      "market_cap_rank": 33
    },
    {
      "symbol": "CRO",
      "name": "Cronos",
      "id": "crypto-com-chain",
      "current_price": 0.1461,
      "price_change_percentage_24h": -1.46971,
      "market_cap_rank": 34
    },
    {
      "symbol": "SUSDE",
      "name": "Ethena Staked USDe",
      "id": "ethena-staked-usde",
      "current_price": 1.2019,
      "price_change_percentage_24h": 0.10378,
      "market_cap_rank": 35
    },
    {
      "symbol": "MNT",
      "name": "Mantle",
      "id": "mantle",
      "current_price": 1.4616,
      "price_change_percentage_24h": -9.21102,
      "market_cap_rank": 36
    },
    {
      "symbol": "DAI",
      "name": "Dai",
      "id": "dai",
      "current_price": 1.0008,
      "price_change_percentage_24h": 0.15389,
      "market_cap_rank": 37
    },
    {
      "symbol": "DOT",
      "name": "Polkadot",
      "id": "polkadot",
      "current_price": 2.896,
      "price_change_percentage_24h": -5.86183,
      "market_cap_rank": 38
    },
    {
      "symbol": "M",
      "name": "MemeCore",
      "id": "memecore",
      "current_price": 2.5142,
      "price_change_percentage_24h": 6.31972,
      "market_cap_rank": 39
    },
    {
      "symbol": "TAO",
      "name": "Bittensor",
      "id": "bittensor",
      "current_price": 438.057,
      "price_change_percentage_24h": -2.43743,
      "market_cap_rank": 40
    },
    {
      "symbol": "WLFI",
      "name": "World Liberty Financial",
      "id": "world-liberty-financial",
      "current_price": 0.1374,
      "price_change_percentage_24h": -3.206,
      "market_cap_rank": 41
    },
    {
      "symbol": "SUSDS",
      "name": "sUSDS",
      "id": "susds",
      "current_price": 1.0734,
      "price_change_percentage_24h": 0.00474,
      "market_cap_rank": 42
    },
    {
      "symbol": "UNI",
      "name": "Uniswap",
      "id": "uniswap",
      "current_price": 5.8852,
      "price_change_percentage_24h": -3.8011,
      "market_cap_rank": 43
    },
    {
      "symbol": "AAVE",
      "name": "Aave",
      "id": "aave",
      "current_price": 217.4133,
      "price_change_percentage_24h": -5.30239,
      "market_cap_rank": 44
    },
    {
      "symbol": "BGB",
      "name": "Bitget Token",
      "id": "bitget-token",
      "current_price": 4.4932,
      "price_change_percentage_24h": -3.42583,
      "market_cap_rank": 45
    },
    {
      "symbol": "FIGR_HELOC",
      "name": "Figure Heloc",
      "id": "figure-heloc",
      "current_price": 0.234,
      "price_change_percentage_24h": -76.57431,
      "market_cap_rank": 46
    },
    {
      "symbol": "OKB",
      "name": "OKB",
      "id": "okb",
      "current_price": 145.565,
      "price_change_percentage_24h": -7.3437,
      "market_cap_rank": 47
    },
    {
      "symbol": "USD1",
      "name": "USD1",
      "id": "usd1-wlfi",
      "current_price": 0.9997,
      "price_change_percentage_24h": -0.06631,
      "market_cap_rank": 48
    },
    {
      "symbol": "BUIDL",
      "name": "BlackRock USD Institutional Digital Liquidity Fund",
      "id": "blackrock-usd-institutional-digital-liquidity-fund",
      "current_price": 1,
      "price_change_percentage_24h": 0,
      "market_cap_rank": 49
    },
    {
      "symbol": "ENA",
      "name": "Ethena",
      "id": "ethena",
      "current_price": 0.3964,
      "price_change_percentage_24h": -7.82312,
      "market_cap_rank": 50
    },
    {
      "symbol": "PYUSD",
      "name": "PayPal USD",
      "id": "paypal-usd",
      "current_price": 0.9999,
      "price_change_percentage_24h": -0.00947,
      "market_cap_rank": 51
    },
    {
      "symbol": "PEPE",
      "name": "Pepe",
      "id": "pepe",
      "current_price": 0,
      "price_change_percentage_24h": -5.75706,
      "market_cap_rank": 52
    },
    {
      "symbol": "NEAR",
      "name": "NEAR Protocol",
      "id": "near",
      "current_price": 2.1102,
      "price_change_percentage_24h": -6.48172,
      "market_cap_rank": 53
    },
    {
      "symbol": "JITOSOL",
      "name": "Jito Staked SOL",
      "id": "jito-staked-sol",
      "current_price": 229.4745,
      "price_change_percentage_24h": -5.42439,
      "market_cap_rank": 54
    },
    {
      "symbol": "ETC",
      "name": "Ethereum Classic",
      "id": "ethereum-classic",
      "current_price": 15.6813,
      "price_change_percentage_24h": -1.86238,
      "market_cap_rank": 55
    },
    {
      "symbol": "SOL",
      "name": "Wrapped SOL",
      "id": "wrapped-solana",
      "current_price": 185.3694,
      "price_change_percentage_24h": -5.20816,
      "market_cap_rank": 56
    },
    {
      "symbol": "APT",
      "name": "Aptos",
      "id": "aptos",
      "current_price": 3.2269,
      "price_change_percentage_24h": -6.29937,
      "market_cap_rank": 57
    },
    {
      "symbol": "WETH",
      "name": "Binance-Peg WETH",
      "id": "binance-peg-weth",
      "current_price": 3832.8468,
      "price_change_percentage_24h": -2.72116,
      "market_cap_rank": 58
    },
    {
      "symbol": "JLP",
      "name": "Jupiter Perpetuals Liquidity Provider Token",
      "id": "jupiter-perpetuals-liquidity-provider-token",
      "current_price": 5.4005,
      "price_change_percentage_24h": -2.36892,
      "market_cap_rank": 59
    },
    {
      "symbol": "ONDO",
      "name": "Ondo",
      "id": "ondo-finance",
      "current_price": 0.6902,
      "price_change_percentage_24h": -5.81149,
      "market_cap_rank": 60
    },
    {
      "symbol": "USDF",
      "name": "Falcon USD",
      "id": "falcon-finance",
      "current_price": 0.9967,
      "price_change_percentage_24h": 0.03032,
      "market_cap_rank": 61
    },
    {
      "symbol": "XAUT",
      "name": "Tether Gold",
      "id": "tether-gold",
      "current_price": 4025.8168,
      "price_change_percentage_24h": 1.85475,
      "market_cap_rank": 62
    },
    {
      "symbol": "PI",
      "name": "Pi Network",
      "id": "pi-network",
      "current_price": 0.2424,
      "price_change_percentage_24h": -7.02584,
      "market_cap_rank": 63
    },
    {
      "symbol": "POL",
      "name": "POL (ex-MATIC)",
      "id": "polygon-ecosystem-token",
      "current_price": 0.1868,
      "price_change_percentage_24h": -3.96418,
      "market_cap_rank": 64
    },
    {
      "symbol": "ASTER",
      "name": "Aster",
      "id": "aster-2",
      "current_price": 0.9425,
      "price_change_percentage_24h": -8.11558,
      "market_cap_rank": 65
    },
    {
      "symbol": "USDTB",
      "name": "USDtb",
      "id": "usdtb",
      "current_price": 0.9994,
      "price_change_percentage_24h": -0.02642,
      "market_cap_rank": 66
    },
    {
      "symbol": "WLD",
      "name": "Worldcoin",
      "id": "worldcoin-wld",
      "current_price": 0.8,
      "price_change_percentage_24h": -6.05718,
      "market_cap_rank": 67
    },
    {
      "symbol": "KCS",
      "name": "KuCoin",
      "id": "kucoin-shares",
      "current_price": 13.2995,
      "price_change_percentage_24h": -0.68376,
      "market_cap_rank": 68
    },
    {
      "symbol": "HTX",
      "name": "HTX DAO",
      "id": "htx-dao",
      "current_price": 0,
      "price_change_percentage_24h": -0.80024,
      "market_cap_rank": 69
    },
    {
      "symbol": "RETH",
      "name": "Rocket Pool ETH",
      "id": "rocket-pool-eth",
      "current_price": 4398.0171,
      "price_change_percentage_24h": -2.71247,
      "market_cap_rank": 70
    },
    {
      "symbol": "BNSOL",
      "name": "Binance Staked SOL",
      "id": "binance-staked-sol",
      "current_price": 200.656,
      "price_change_percentage_24h": -5.08695,
      "market_cap_rank": 71
    },
    {
      "symbol": "TRUMP",
      "name": "Official Trump",
      "id": "official-trump",
      "current_price": 8.0796,
      "price_change_percentage_24h": -2.98297,
      "market_cap_rank": 72
    },
    {
      "symbol": "ARB",
      "name": "Arbitrum",
      "id": "arbitrum",
      "current_price": 0.2925,
      "price_change_percentage_24h": -7.60432,
      "market_cap_rank": 73
    },
    {
      "symbol": "KHYPE",
      "name": "Kinetiq Staked HYPE",
      "id": "kinetic-staked-hype",
      "current_price": 44.3338,
      "price_change_percentage_24h": -10.79659,
      "market_cap_rank": 74
    },
    {
      "symbol": "ICP",
      "name": "Internet Computer",
      "id": "internet-computer",
      "current_price": 2.9096,
      "price_change_percentage_24h": -4.30649,
      "market_cap_rank": 75
    },
    {
      "symbol": "GT",
      "name": "Gate",
      "id": "gatechain-token",
      "current_price": 13.2618,
      "price_change_percentage_24h": -5.72897,
      "market_cap_rank": 76
    },
    {
      "symbol": "ALGO",
      "name": "Algorand",
      "id": "algorand",
      "current_price": 0.1758,
      "price_change_percentage_24h": -4.99566,
      "market_cap_rank": 77
    },
    {
      "symbol": "PUMP",
      "name": "Pump.fun",
      "id": "pump-fun",
      "current_price": 0.0043,
      "price_change_percentage_24h": -14.94238,
      "market_cap_rank": 78
    },
    {
      "symbol": "HASH",
      "name": "Provenance Blockchain",
      "id": "hash-2",
      "current_price": 0.0293,
      "price_change_percentage_24h": -6.56735,
      "market_cap_rank": 79
    },
    {
      "symbol": "RSETH",
      "name": "Kelp DAO Restaked ETH",
      "id": "kelp-dao-restaked-eth",
      "current_price": 4055.5542,
      "price_change_percentage_24h": -2.57245,
      "market_cap_rank": 80
    },
    {
      "symbol": "OSETH",
      "name": "StakeWise Staked ETH",
      "id": "stakewise-v3-oseth",
      "current_price": 4052.2995,
      "price_change_percentage_24h": -2.57263,
      "market_cap_rank": 81
    },
    {
      "symbol": "KAS",
      "name": "Kaspa",
      "id": "kaspa",
      "current_price": 0.0538,
      "price_change_percentage_24h": -6.35879,
      "market_cap_rank": 82
    },
    {
      "symbol": "ATOM",
      "name": "Cosmos Hub",
      "id": "cosmos",
      "current_price": 2.9904,
      "price_change_percentage_24h": -4.13974,
      "market_cap_rank": 83
    },
    {
      "symbol": "IP",
      "name": "Story",
      "id": "story-2",
      "current_price": 4.4053,
      "price_change_percentage_24h": -6.58085,
      "market_cap_rank": 84
    },
    {
      "symbol": "SYRUPUSDT",
      "name": "syrupUSDT",
      "id": "syrupusdt",
      "current_price": 1.0997,
      "price_change_percentage_24h": -0.03746,
      "market_cap_rank": 85
    },
    {
      "symbol": "LSETH",
      "name": "Liquid Staked ETH",
      "id": "liquid-staked-ethereum",
      "current_price": 4117.3863,
      "price_change_percentage_24h": -2.67578,
      "market_cap_rank": 86
    },
    {
      "symbol": "WBNB",
      "name": "Wrapped BNB",
      "id": "wbnb",
      "current_price": 1098.7182,
      "price_change_percentage_24h": -1.71174,
      "market_cap_rank": 87
    },
    {
      "symbol": "VET",
      "name": "VeChain",
      "id": "vechain",
      "current_price": 0.0158,
      "price_change_percentage_24h": -5.19207,
      "market_cap_rank": 88
    },
    {
      "symbol": "SYRUPUSDC",
      "name": "syrupUSDC",
      "id": "syrupusdc",
      "current_price": 1.1338,
      "price_change_percentage_24h": 0.01343,
      "market_cap_rank": 89
    },
    {
      "symbol": "PAXG",
      "name": "PAX Gold",
      "id": "pax-gold",
      "current_price": 4023.3339,
      "price_change_percentage_24h": 1.58144,
      "market_cap_rank": 90
    },
    {
      "symbol": "LBTC",
      "name": "Lombard Staked BTC",
      "id": "lombard-staked-btc",
      "current_price": 109736.3472,
      "price_change_percentage_24h": -1.26878,
      "market_cap_rank": 91
    },
    {
      "symbol": "SKY",
      "name": "Sky",
      "id": "sky",
      "current_price": 0.0567,
      "price_change_percentage_24h": -5.11306,
      "market_cap_rank": 92
    },
    {
      "symbol": "BFUSD",
      "name": "BFUSD",
      "id": "bfusd",
      "current_price": 0.9997,
      "price_change_percentage_24h": -0.02503,
      "market_cap_rank": 93
    },
    {
      "symbol": "JUP",
      "name": "Jupiter",
      "id": "jupiter-exchange-solana",
      "current_price": 0.4011,
      "price_change_percentage_24h": -6.24988,
      "market_cap_rank": 94
    },
    {
      "symbol": "FLR",
      "name": "Flare",
      "id": "flare-networks",
      "current_price": 0.0162,
      "price_change_percentage_24h": -3.20766,
      "market_cap_rank": 95
    },
    {
      "symbol": "EZETH",
      "name": "Renzo Restaked ETH",
      "id": "renzo-restaked-eth",
      "current_price": 4076.4317,
      "price_change_percentage_24h": -2.60069,
      "market_cap_rank": 96
    },
    {
      "symbol": "PENGU",
      "name": "Pudgy Penguins",
      "id": "pudgy-penguins",
      "current_price": 0.0187,
      "price_change_percentage_24h": -10.61103,
      "market_cap_rank": 97
    },
    {
      "symbol": "QNT",
      "name": "Quant",
      "id": "quant-network",
      "current_price": 80.6075,
      "price_change_percentage_24h": -0.89435,
      "market_cap_rank": 98
    },
    {
      "symbol": "RENDER",
      "name": "Render",
      "id": "render-token",
      "current_price": 2.2478,
      "price_change_percentage_24h": -6.4171,
      "market_cap_rank": 99
    },
    {
      "symbol": "SEI",
      "name": "Sei",
      "id": "sei-network",
      "current_price": 0.1864,
      "price_change_percentage_24h": -5.18814,
      "market_cap_rank": 100
    },
    {
      "symbol": "USDC",
      "name": "Binance Bridged USDC (BNB Smart Chain)",
      "id": "binance-bridged-usdc-bnb-smart-chain",
      "current_price": 1.0002,
      "price_change_percentage_24h": 0.03095,
      "market_cap_rank": 101
    },
    {
      "symbol": "SOLVBTC",
      "name": "Solv Protocol BTC",
      "id": "solv-btc",
      "current_price": 109331.9813,
      "price_change_percentage_24h": -1.4117,
      "market_cap_rank": 102
    },
    {
      "symbol": "NEXO",
      "name": "NEXO",
      "id": "nexo",
      "current_price": 1.1018,
      "price_change_percentage_24h": -3.34975,
      "market_cap_rank": 103
    },
    {
      "symbol": "FIL",
      "name": "Filecoin",
      "id": "filecoin",
      "current_price": 1.5179,
      "price_change_percentage_24h": -3.3553,
      "market_cap_rank": 104
    },
    {
      "symbol": "XDC",
      "name": "XDC Network",
      "id": "xdce-crowd-sale",
      "current_price": 0.0595,
      "price_change_percentage_24h": -1.5339,
      "market_cap_rank": 105
    },
    {
      "symbol": "BONK",
      "name": "Bonk",
      "id": "bonk",
      "current_price": 0,
      "price_change_percentage_24h": -5.71621,
      "market_cap_rank": 106
    },
    {
      "symbol": "MORPHO",
      "name": "Morpho",
      "id": "morpho",
      "current_price": 1.9881,
      "price_change_percentage_24h": -0.0425,
      "market_cap_rank": 107
    },
    {
      "symbol": "FDUSD",
      "name": "First Digital USD",
      "id": "first-digital-usd",
      "current_price": 0.9977,
      "price_change_percentage_24h": -0.06609,
      "market_cap_rank": 108
    },
    {
      "symbol": "USDG",
      "name": "Global Dollar",
      "id": "global-dollar",
      "current_price": 0.9998,
      "price_change_percentage_24h": -0.0194,
      "market_cap_rank": 109
    },
    {
      "symbol": "AERO",
      "name": "Aerodrome Finance",
      "id": "aerodrome-finance",
      "current_price": 1.0747,
      "price_change_percentage_24h": -0.00156,
      "market_cap_rank": 110
    },
    {
      "symbol": "IMX",
      "name": "Immutable",
      "id": "immutable-x",
      "current_price": 0.4927,
      "price_change_percentage_24h": -5.10657,
      "market_cap_rank": 111
    },
    {
      "symbol": "METH",
      "name": "Mantle Staked Ether",
      "id": "mantle-staked-ether",
      "current_price": 4127.3856,
      "price_change_percentage_24h": -2.78338,
      "market_cap_rank": 112
    },
    {
      "symbol": "JUPSOL",
      "name": "Jupiter Staked SOL",
      "id": "jupiter-staked-sol",
      "current_price": 212.427,
      "price_change_percentage_24h": -5.37463,
      "market_cap_rank": 113
    },
    {
      "symbol": "RLUSD",
      "name": "Ripple USD",
      "id": "ripple-usd",
      "current_price": 1.0001,
      "price_change_percentage_24h": -0.00748,
      "market_cap_rank": 114
    },
    {
      "symbol": "WBTC",
      "name": "Arbitrum Bridged WBTC (Arbitrum One)",
      "id": "arbitrum-bridged-wbtc-arbitrum-one",
      "current_price": 109650.5976,
      "price_change_percentage_24h": -1.40977,
      "market_cap_rank": 115
    },
    {
      "symbol": "VIRTUAL",
      "name": "Virtuals Protocol",
      "id": "virtual-protocol",
      "current_price": 1.3501,
      "price_change_percentage_24h": -9.98355,
      "market_cap_rank": 116
    },
    {
      "symbol": "FTN",
      "name": "Fasttoken",
      "id": "fasttoken",
      "current_price": 2.015,
      "price_change_percentage_24h": 6.78281,
      "market_cap_rank": 117
    },
    {
      "symbol": "CLBTC",
      "name": "clBTC",
      "id": "clbtc",
      "current_price": 110741.6698,
      "price_change_percentage_24h": 2.62096,
      "market_cap_rank": 118
    },
    {
      "symbol": "SPX",
      "name": "SPX6900",
      "id": "spx6900",
      "current_price": 0.9083,
      "price_change_percentage_24h": -7.86281,
      "market_cap_rank": 119
    },
    {
      "symbol": "CAKE",
      "name": "PancakeSwap",
      "id": "pancakeswap-token",
      "current_price": 2.4277,
      "price_change_percentage_24h": -6.52364,
      "market_cap_rank": 120
    },
    {
      "symbol": "USYC",
      "name": "Circle USYC",
      "id": "hashnote-usyc",
      "current_price": 1.1044,
      "price_change_percentage_24h": null,
      "market_cap_rank": 121
    },
    {
      "symbol": "OUSG",
      "name": "OUSG",
      "id": "ousg",
      "current_price": 113.1177,
      "price_change_percentage_24h": 0.01039,
      "market_cap_rank": 122
    },
    {
      "symbol": "MSOL",
      "name": "Marinade Staked SOL",
      "id": "msol",
      "current_price": 247.0837,
      "price_change_percentage_24h": -5.45576,
      "market_cap_rank": 123
    },
    {
      "symbol": "LDO",
      "name": "Lido DAO",
      "id": "lido-dao",
      "current_price": 0.8537,
      "price_change_percentage_24h": -5.83949,
      "market_cap_rank": 124
    },
    {
      "symbol": "INJ",
      "name": "Injective",
      "id": "injective-protocol",
      "current_price": 7.7757,
      "price_change_percentage_24h": -7.58861,
      "market_cap_rank": 125
    },
    {
      "symbol": "TIA",
      "name": "Celestia",
      "id": "celestia",
      "current_price": 0.913,
      "price_change_percentage_24h": -8.38901,
      "market_cap_rank": 126
    },
    {
      "symbol": "OP",
      "name": "Optimism",
      "id": "optimism",
      "current_price": 0.3992,
      "price_change_percentage_24h": -8.62721,
      "market_cap_rank": 127
    },
    {
      "symbol": "STX",
      "name": "Stacks",
      "id": "blockstack",
      "current_price": 0.4115,
      "price_change_percentage_24h": -6.22856,
      "market_cap_rank": 128
    },
    {
      "symbol": "USTB",
      "name": "Superstate Short Duration U.S. Government Securities Fund (USTB)",
      "id": "superstate-short-duration-us-government-securities-fund-ustb",
      "current_price": 10.8747,
      "price_change_percentage_24h": 0.01041,
      "market_cap_rank": 129
    },
    {
      "symbol": "CRV",
      "name": "Curve DAO",
      "id": "curve-dao-token",
      "current_price": 0.4896,
      "price_change_percentage_24h": -8.80046,
      "market_cap_rank": 130
    },
    {
      "symbol": "USDX",
      "name": "Stables Labs USDX",
      "id": "usdx-money-usdx",
      "current_price": 0.9986,
      "price_change_percentage_24h": -0.01151,
      "market_cap_rank": 131
    },
    {
      "symbol": "USDY",
      "name": "Ondo US Dollar Yield",
      "id": "ondo-us-dollar-yield",
      "current_price": 1.0978,
      "price_change_percentage_24h": 1.27278,
      "market_cap_rank": 132
    },
    {
      "symbol": "WETH",
      "name": "L2 Standard Bridged WETH (Base)",
      "id": "l2-standard-bridged-weth-base",
      "current_price": 3833.9558,
      "price_change_percentage_24h": -2.64612,
      "market_cap_rank": 133
    },
    {
      "symbol": "LIQUIDETH",
      "name": "Ether.Fi Liquid ETH",
      "id": "ether-fi-liquid-eth",
      "current_price": 4058.2569,
      "price_change_percentage_24h": -2.75391,
      "market_cap_rank": 134
    },
    {
      "symbol": "FLOKI",
      "name": "FLOKI",
      "id": "floki",
      "current_price": 0.0001,
      "price_change_percentage_24h": -3.54503,
      "market_cap_rank": 135
    },
    {
      "symbol": "2Z",
      "name": "DoubleZero",
      "id": "doublezero",
      "current_price": 0.19,
      "price_change_percentage_24h": -9.23477,
      "market_cap_rank": 136
    },
    {
      "symbol": "TBTC",
      "name": "tBTC",
      "id": "tbtc",
      "current_price": 109376.8551,
      "price_change_percentage_24h": -1.01324,
      "market_cap_rank": 137
    },
    {
      "symbol": "GRT",
      "name": "The Graph",
      "id": "the-graph",
      "current_price": 0.0614,
      "price_change_percentage_24h": -3.77592,
      "market_cap_rank": 138
    },
    {
      "symbol": "FET",
      "name": "Artificial Superintelligence Alliance",
      "id": "fetch-ai",
      "current_price": 0.2397,
      "price_change_percentage_24h": -7.56312,
      "market_cap_rank": 139
    },
    {
      "symbol": "WETH",
      "name": "Arbitrum Bridged WETH (Arbitrum One)",
      "id": "arbitrum-bridged-weth-arbitrum-one",
      "current_price": 3837.6182,
      "price_change_percentage_24h": -2.48185,
      "market_cap_rank": 140
    },
    {
      "symbol": "XTZ",
      "name": "Tezos",
      "id": "tezos",
      "current_price": 0.5686,
      "price_change_percentage_24h": -3.53771,
      "market_cap_rank": 141
    },
    {
      "symbol": "KAIA",
      "name": "Kaia",
      "id": "kaia",
      "current_price": 0.1028,
      "price_change_percentage_24h": -3.5567,
      "market_cap_rank": 142
    },
    {
      "symbol": "BDX",
      "name": "Beldex",
      "id": "beldex",
      "current_price": 0.0801,
      "price_change_percentage_24h": 0.51266,
      "market_cap_rank": 143
    },
    {
      "symbol": "DASH",
      "name": "Dash",
      "id": "dash",
      "current_price": 47.8846,
      "price_change_percentage_24h": 3.24651,
      "market_cap_rank": 144
    },
    {
      "symbol": "ETHX",
      "name": "Stader ETHx",
      "id": "stader-ethx",
      "current_price": 4111.9822,
      "price_change_percentage_24h": -2.62661,
      "market_cap_rank": 145
    },
    {
      "symbol": "PYTH",
      "name": "Pyth Network",
      "id": "pyth-network",
      "current_price": 0.1028,
      "price_change_percentage_24h": -8.71912,
      "market_cap_rank": 146
    },
    {
      "symbol": "GTETH",
      "name": "GTETH",
      "id": "gteth",
      "current_price": 3831.3089,
      "price_change_percentage_24h": -2.49581,
      "market_cap_rank": 147
    },
    {
      "symbol": "USDAI",
      "name": "USDai",
      "id": "usdai",
      "current_price": 1.0089,
      "price_change_percentage_24h": -0.17068,
      "market_cap_rank": 148
    },
    {
      "symbol": "USDC.E",
      "name": "Polygon Bridged USDC (Polygon PoS)",
      "id": "bridged-usdc-polygon-pos-bridge",
      "current_price": 0.9997,
      "price_change_percentage_24h": -0.00706,
      "market_cap_rank": 149
    },
    {
      "symbol": "IOTA",
      "name": "IOTA",
      "id": "iota",
      "current_price": 0.1379,
      "price_change_percentage_24h": -3.04594,
      "market_cap_rank": 150
    },
    {
      "symbol": "DAI",
      "name": "Polygon PoS Bridged DAI (Polygon POS)",
      "id": "polygon-pos-bridged-dai-polygon-pos",
      "current_price": 0.9996,
      "price_change_percentage_24h": -0.01782,
      "market_cap_rank": 151
    },
    {
      "symbol": "XPL",
      "name": "Plasma",
      "id": "plasma",
      "current_price": 0.2939,
      "price_change_percentage_24h": -4.8524,
      "market_cap_rank": 152
    },
    {
      "symbol": "USD0",
      "name": "Usual USD",
      "id": "usual-usd",
      "current_price": 0.9981,
      "price_change_percentage_24h": 0.00298,
      "market_cap_rank": 153
    },
    {
      "symbol": "S",
      "name": "Sonic",
      "id": "sonic-3",
      "current_price": 0.1406,
      "price_change_percentage_24h": -10.72933,
      "market_cap_rank": 154
    },
    {
      "symbol": "AB",
      "name": "AB",
      "id": "newton-project",
      "current_price": 0.0063,
      "price_change_percentage_24h": -1.76633,
      "market_cap_rank": 155
    },
    {
      "symbol": "CBETH",
      "name": "Coinbase Wrapped Staked ETH",
      "id": "coinbase-wrapped-staked-eth",
      "current_price": 4218.2256,
      "price_change_percentage_24h": -2.68593,
      "market_cap_rank": 156
    },
    {
      "symbol": "CFX",
      "name": "Conflux",
      "id": "conflux-token",
      "current_price": 0.1016,
      "price_change_percentage_24h": -6.59592,
      "market_cap_rank": 157
    },
    {
      "symbol": "ETHFI",
      "name": "Ether.fi",
      "id": "ether-fi",
      "current_price": 0.9274,
      "price_change_percentage_24h": -3.66717,
      "market_cap_rank": 158
    },
    {
      "symbol": "PENDLE",
      "name": "Pendle",
      "id": "pendle",
      "current_price": 3.078,
      "price_change_percentage_24h": -7.03748,
      "market_cap_rank": 159
    },
    {
      "symbol": "SWETH",
      "name": "Swell Ethereum",
      "id": "sweth",
      "current_price": 4223.9053,
      "price_change_percentage_24h": -2.75801,
      "market_cap_rank": 160
    },
    {
      "symbol": "BTC.B",
      "name": "Avalanche Bridged BTC (Avalanche)",
      "id": "bitcoin-avalanche-bridged-btc-b",
      "current_price": 109457.0071,
      "price_change_percentage_24h": -1.63967,
      "market_cap_rank": 161
    },
    {
      "symbol": "TWT",
      "name": "Trust Wallet",
      "id": "trust-wallet-token",
      "current_price": 1.2214,
      "price_change_percentage_24h": -2.24445,
      "market_cap_rank": 162
    },
    {
      "symbol": "USDT",
      "name": "Mantle Bridged USDT (Mantle)",
      "id": "mantle-bridged-usdt-mantle",
      "current_price": 0.9989,
      "price_change_percentage_24h": -0.52469,
      "market_cap_rank": 163
    },
    {
      "symbol": "WIF",
      "name": "dogwifhat",
      "id": "dogwifcoin",
      "current_price": 0.5009,
      "price_change_percentage_24h": -5.91454,
      "market_cap_rank": 164
    },
    {
      "symbol": "H",
      "name": "Humanity",
      "id": "humanity",
      "current_price": 0.2718,
      "price_change_percentage_24h": -0.32325,
      "market_cap_rank": 165
    },
    {
      "symbol": "TUSD",
      "name": "TrueUSD",
      "id": "true-usd",
      "current_price": 0.9981,
      "price_change_percentage_24h": 0.12105,
      "market_cap_rank": 166
    },
    {
      "symbol": "WHYPE",
      "name": "Wrapped HYPE",
      "id": "wrapped-hype",
      "current_price": 44.1597,
      "price_change_percentage_24h": -10.31336,
      "market_cap_rank": 167
    },
    {
      "symbol": "SAND",
      "name": "The Sandbox",
      "id": "the-sandbox",
      "current_price": 0.2003,
      "price_change_percentage_24h": -4.84661,
      "market_cap_rank": 168
    },
    {
      "symbol": "JASMY",
      "name": "JasmyCoin",
      "id": "jasmycoin",
      "current_price": 0.0101,
      "price_change_percentage_24h": -1.52041,
      "market_cap_rank": 169
    },
    {
      "symbol": "THETA",
      "name": "Theta Network",
      "id": "theta-token",
      "current_price": 0.4878,
      "price_change_percentage_24h": -6.13773,
      "market_cap_rank": 170
    },
    {
      "symbol": "ENS",
      "name": "Ethereum Name Service",
      "id": "ethereum-name-service",
      "current_price": 14.719,
      "price_change_percentage_24h": -5.08464,
      "market_cap_rank": 171
    },
    {
      "symbol": "STEAKUSDC",
      "name": "Steakhouse USDC Morpho Vault",
      "id": "steakhouse-usdc-morpho-vault",
      "current_price": 1.1066,
      "price_change_percentage_24h": 0.09778,
      "market_cap_rank": 172
    },
    {
      "symbol": "SYRUP",
      "name": "Maple Finance",
      "id": "syrup",
      "current_price": 0.4291,
      "price_change_percentage_24h": -2.08647,
      "market_cap_rank": 173
    },
    {
      "symbol": "DOGE",
      "name": "Binance-Peg Dogecoin",
      "id": "binance-peg-dogecoin",
      "current_price": 0.1844,
      "price_change_percentage_24h": -4.07578,
      "market_cap_rank": 174
    },
    {
      "symbol": "ASBNB",
      "name": "Aster Staked BNB",
      "id": "astherus-staked-bnb",
      "current_price": 1160.5449,
      "price_change_percentage_24h": -1.74731,
      "market_cap_rank": 175
    },
    {
      "symbol": "STRK",
      "name": "Starknet",
      "id": "starknet",
      "current_price": 0.1087,
      "price_change_percentage_24h": -6.74622,
      "market_cap_rank": 176
    },
    {
      "symbol": "BTT",
      "name": "BitTorrent",
      "id": "bittorrent",
      "current_price": 0,
      "price_change_percentage_24h": -4.32693,
      "market_cap_rank": 177
    },
    {
      "symbol": "GALA",
      "name": "GALA",
      "id": "gala",
      "current_price": 0.0101,
      "price_change_percentage_24h": -6.02509,
      "market_cap_rank": 178
    },
    {
      "symbol": "EETH",
      "name": "ether.fi Staked ETH",
      "id": "ether-fi-staked-eth",
      "current_price": 3828.5944,
      "price_change_percentage_24h": -2.7294,
      "market_cap_rank": 179
    },
    {
      "symbol": "HNT",
      "name": "Helium",
      "id": "helium",
      "current_price": 2.4376,
      "price_change_percentage_24h": 2.22369,
      "market_cap_rank": 180
    },
    {
      "symbol": "RAY",
      "name": "Raydium",
      "id": "raydium",
      "current_price": 1.6649,
      "price_change_percentage_24h": -6.14657,
      "market_cap_rank": 181
    },
    {
      "symbol": "WEETH",
      "name": "Arbitrum Bridged Wrapped eETH (Arbitrum)",
      "id": "arbitrum-bridged-wrapped-eeth",
      "current_price": 4138.079,
      "price_change_percentage_24h": -2.58523,
      "market_cap_rank": 182
    },
    {
      "symbol": "BSV",
      "name": "Bitcoin SV",
      "id": "bitcoin-cash-sv",
      "current_price": 22.1203,
      "price_change_percentage_24h": -0.95986,
      "market_cap_rank": 183
    },
    {
      "symbol": "USDD",
      "name": "USDD",
      "id": "usdd",
      "current_price": 0.9997,
      "price_change_percentage_24h": -0.02273,
      "market_cap_rank": 184
    },
    {
      "symbol": "MANA",
      "name": "Decentraland",
      "id": "decentraland",
      "current_price": 0.2271,
      "price_change_percentage_24h": -3.0409,
      "market_cap_rank": 185
    },
    {
      "symbol": "GHO",
      "name": "GHO",
      "id": "gho",
      "current_price": 0.9994,
      "price_change_percentage_24h": -0.02306,
      "market_cap_rank": 186
    },
    {
      "symbol": "A",
      "name": "Vaulta",
      "id": "vaulta",
      "current_price": 0.2662,
      "price_change_percentage_24h": -5.62585,
      "market_cap_rank": 187
    },
    {
      "symbol": "SAVAX",
      "name": "BENQI Liquid Staked AVAX",
      "id": "benqi-liquid-staked-avax",
      "current_price": 22.5317,
      "price_change_percentage_24h": -7.85525,
      "market_cap_rank": 188
    },
    {
      "symbol": "SUN",
      "name": "Sun Token",
      "id": "sun-token",
      "current_price": 0.022,
      "price_change_percentage_24h": -2.33152,
      "market_cap_rank": 189
    },
    {
      "symbol": "FLOW",
      "name": "Flow",
      "id": "flow",
      "current_price": 0.2612,
      "price_change_percentage_24h": -3.06302,
      "market_cap_rank": 190
    },
    {
      "symbol": "BORG",
      "name": "SwissBorg",
      "id": "swissborg",
      "current_price": 0.427,
      "price_change_percentage_24h": -2.31574,
      "market_cap_rank": 191
    },
    {
      "symbol": "WETH",
      "name": "Polygon PoS Bridged WETH (Polygon POS)",
      "id": "polygon-pos-bridged-weth-polygon-pos",
      "current_price": 3834.1755,
      "price_change_percentage_24h": -2.55758,
      "market_cap_rank": 192
    },
    {
      "symbol": "CMETH",
      "name": "Mantle Restaked ETH",
      "id": "mantle-restaked-eth",
      "current_price": 4119.0551,
      "price_change_percentage_24h": -3.25846,
      "market_cap_rank": 193
    },
    {
      "symbol": "VKHYPE",
      "name": "Kinetiq Earn Vault",
      "id": "kinetiq-earn-vault",
      "current_price": 44.5552,
      "price_change_percentage_24h": -11.01115,
      "market_cap_rank": 194
    },
    {
      "symbol": "EIGEN",
      "name": "EigenCloud (prev. EigenLayer)",
      "id": "eigenlayer",
      "current_price": 0.9282,
      "price_change_percentage_24h": -13.16457,
      "market_cap_rank": 195
    },
    {
      "symbol": "USDB",
      "name": "USDB",
      "id": "usdb",
      "current_price": 0.99,
      "price_change_percentage_24h": -0.57657,
      "market_cap_rank": 196
    },
    {
      "symbol": "SN115",
      "name": "Cognify",
      "id": "cognify",
      "current_price": 1762.4681,
      "price_change_percentage_24h": 0,
      "market_cap_rank": 197
    },
    {
      "symbol": "NFT",
      "name": "AINFT",
      "id": "apenft",
      "current_price": 0,
      "price_change_percentage_24h": -1.62289,
      "market_cap_rank": 198
    },
    {
      "symbol": "MYX",
      "name": "MYX Finance",
      "id": "myx-finance",
      "current_price": 2.1032,
      "price_change_percentage_24h": -9.06201,
      "market_cap_rank": 199
    },
    {
      "symbol": "SATUSD",
      "name": "Satoshi Stablecoin",
      "id": "satoshi-stablecoin",
      "current_price": 0.9994,
      "price_change_percentage_24h": -0.17532,
      "market_cap_rank": 200
    },
    {
      "symbol": "ARK",
      "name": "ARK",
      "id": "ark-3",
      "current_price": 38.9136,
      "price_change_percentage_24h": 0.61866,
      "market_cap_rank": 201
    },
    {
      "symbol": "FRXETH",
      "name": "Frax Ether",
      "id": "frax-ether",
      "current_price": 3783.4275,
      "price_change_percentage_24h": -2.96511,
      "market_cap_rank": 202
    },
    {
      "symbol": "ATONE",
      "name": "AtomOne",
      "id": "atomone",
      "current_price": 3.1601,
      "price_change_percentage_24h": 10.32355,
      "market_cap_rank": 203
    },
    {
      "symbol": "ATH",
      "name": "Aethir",
      "id": "aethir",
      "current_price": 0.0266,
      "price_change_percentage_24h": -4.3495,
      "market_cap_rank": 204
    },
    {
      "symbol": "AXYC",
      "name": "AxyCoin",
      "id": "axycoin",
      "current_price": 1.8823,
      "price_change_percentage_24h": 0.77155,
      "market_cap_rank": 205
    },
    {
      "symbol": "DEXE",
      "name": "DeXe",
      "id": "dexe",
      "current_price": 6.4999,
      "price_change_percentage_24h": -0.497,
      "market_cap_rank": 206
    },
    {
      "symbol": "SDAI",
      "name": "Savings Dai",
      "id": "savings-dai",
      "current_price": 1.1674,
      "price_change_percentage_24h": -0.01865,
      "market_cap_rank": 207
    },
    {
      "symbol": "EUTBL",
      "name": "Spiko EU T-Bills Money Market Fund",
      "id": "eutbl",
      "current_price": 1.2044,
      "price_change_percentage_24h": -0.46301,
      "market_cap_rank": 208
    },
    {
      "symbol": "OHM",
      "name": "Olympus",
      "id": "olympus",
      "current_price": 22.2961,
      "price_change_percentage_24h": -2.04303,
      "market_cap_rank": 209
    },
    {
      "symbol": "VSN",
      "name": "Vision",
      "id": "vision-3",
      "current_price": 0.1085,
      "price_change_percentage_24h": -1.05888,
      "market_cap_rank": 210
    },
    {
      "symbol": "COAI",
      "name": "ChainOpera AI",
      "id": "chainopera-ai",
      "current_price": 1.8432,
      "price_change_percentage_24h": -31.56668,
      "market_cap_rank": 211
    },
    {
      "symbol": "APE",
      "name": "ApeCoin",
      "id": "apecoin",
      "current_price": 0.397,
      "price_change_percentage_24h": -5.91757,
      "market_cap_rank": 212
    },
    {
      "symbol": "UBTC",
      "name": "Unit Bitcoin",
      "id": "unit-bitcoin",
      "current_price": 109375.7069,
      "price_change_percentage_24h": -1.79678,
      "market_cap_rank": 213
    },
    {
      "symbol": "JTO",
      "name": "Jito",
      "id": "jito-governance-token",
      "current_price": 0.9019,
      "price_change_percentage_24h": -15.0224,
      "market_cap_rank": 214
    },
    {
      "symbol": "ZBCN",
      "name": "Zebec Network",
      "id": "zebec-network",
      "current_price": 0.0037,
      "price_change_percentage_24h": -2.72762,
      "market_cap_rank": 215
    },
    {
      "symbol": "NEO",
      "name": "NEO",
      "id": "neo",
      "current_price": 4.9596,
      "price_change_percentage_24h": -3.70114,
      "market_cap_rank": 216
    },
    {
      "symbol": "TIBBIR",
      "name": "Ribbita by Virtuals",
      "id": "ribbita-by-virtuals",
      "current_price": 0.3441,
      "price_change_percentage_24h": -7.53852,
      "market_cap_rank": 217
    },
    {
      "symbol": "ETH+",
      "name": "ETHPlus",
      "id": "reserve-protocol-eth-plus",
      "current_price": 4053.3852,
      "price_change_percentage_24h": -2.61921,
      "market_cap_rank": 218
    },
    {
      "symbol": "JST",
      "name": "JUST",
      "id": "just",
      "current_price": 0.035,
      "price_change_percentage_24h": -0.07436,
      "market_cap_rank": 219
    },
    {
      "symbol": "SNX",
      "name": "Synthetix",
      "id": "havven",
      "current_price": 1.0051,
      "price_change_percentage_24h": -6.20473,
      "market_cap_rank": 220
    },
    {
      "symbol": "GNO",
      "name": "Gnosis",
      "id": "gnosis",
      "current_price": 129.2674,
      "price_change_percentage_24h": -2.60427,
      "market_cap_rank": 221
    },
    {
      "symbol": "TETH",
      "name": "Treehouse ETH",
      "id": "treehouse-eth",
      "current_price": 4685.4498,
      "price_change_percentage_24h": -2.53103,
      "market_cap_rank": 222
    },
    {
      "symbol": "MERL",
      "name": "Merlin Chain",
      "id": "merlin-chain",
      "current_price": 0.3315,
      "price_change_percentage_24h": -3.71344,
      "market_cap_rank": 223
    },
    {
      "symbol": "COMP",
      "name": "Compound",
      "id": "compound-governance-token",
      "current_price": 34.945,
      "price_change_percentage_24h": -5.7503,
      "market_cap_rank": 224
    },
    {
      "symbol": "FLUID",
      "name": "Fluid",
      "id": "instadapp",
      "current_price": 4.3253,
      "price_change_percentage_24h": -5.9151,
      "market_cap_rank": 225
    },
    {
      "symbol": "FARTCOIN",
      "name": "Fartcoin",
      "id": "fartcoin",
      "current_price": 0.3364,
      "price_change_percentage_24h": -9.62493,
      "market_cap_rank": 226
    },
    {
      "symbol": "BBSOL",
      "name": "Bybit Staked SOL",
      "id": "bybit-staked-sol",
      "current_price": 206.9397,
      "price_change_percentage_24h": -5.05472,
      "market_cap_rank": 227
    },
    {
      "symbol": "WAVAX",
      "name": "Wrapped AVAX",
      "id": "wrapped-avax",
      "current_price": 18.2634,
      "price_change_percentage_24h": -7.89241,
      "market_cap_rank": 228
    },
    {
      "symbol": "ZORA",
      "name": "Zora",
      "id": "zora",
      "current_price": 0.0739,
      "price_change_percentage_24h": -6.30633,
      "market_cap_rank": 229
    },
    {
      "symbol": "LION",
      "name": "Loaded Lions",
      "id": "loaded-lions",
      "current_price": 0.0105,
      "price_change_percentage_24h": -2.2095,
      "market_cap_rank": 230
    },
    {
      "symbol": "CGETH.HASHKEY",
      "name": "cgETH Hashkey Cloud",
      "id": "cgeth-hashkey-cloud",
      "current_price": 1605.9028,
      "price_change_percentage_24h": null,
      "market_cap_rank": 231
    },
    {
      "symbol": "TEL",
      "name": "Telcoin",
      "id": "telcoin",
      "current_price": 0.0033,
      "price_change_percentage_24h": -5.14083,
      "market_cap_rank": 232
    },
    {
      "symbol": "DSOL",
      "name": "Drift Staked SOL",
      "id": "drift-staked-sol",
      "current_price": 213.7946,
      "price_change_percentage_24h": -5.19845,
      "market_cap_rank": 233
    },
    {
      "symbol": "WAL",
      "name": "Walrus",
      "id": "walrus-2",
      "current_price": 0.214,
      "price_change_percentage_24h": -2.87837,
      "market_cap_rank": 234
    },
    {
      "symbol": "WETH",
      "name": "Mantle Bridged WETH (Mantle)",
      "id": "wrapped-ether-mantle-bridge",
      "current_price": 3827.9407,
      "price_change_percentage_24h": -3.0314,
      "market_cap_rank": 235
    },
    {
      "symbol": "BUSD",
      "name": "Binance-Peg BUSD",
      "id": "binance-peg-busd",
      "current_price": 1.0002,
      "price_change_percentage_24h": -0.17213,
      "market_cap_rank": 236
    },
    {
      "symbol": "TRAC",
      "name": "OriginTrail",
      "id": "origintrail",
      "current_price": 0.6247,
      "price_change_percentage_24h": -12.114,
      "market_cap_rank": 237
    },
    {
      "symbol": "SENA",
      "name": "Ethena Staked ENA",
      "id": "ethena-staked-ena",
      "current_price": 0.4028,
      "price_change_percentage_24h": -7.25048,
      "market_cap_rank": 238
    },
    {
      "symbol": "RSR",
      "name": "Reserve Rights",
      "id": "reserve-rights-token",
      "current_price": 0.0051,
      "price_change_percentage_24h": -7.35672,
      "market_cap_rank": 239
    },
    {
      "symbol": "XSOLVBTC",
      "name": "Solv Protocol Staked BTC",
      "id": "solv-protocol-solvbtc-bbn",
      "current_price": 109159.4786,
      "price_change_percentage_24h": -0.65674,
      "market_cap_rank": 240
    },
    {
      "symbol": "W",
      "name": "Wormhole",
      "id": "wormhole",
      "current_price": 0.0635,
      "price_change_percentage_24h": -6.83298,
      "market_cap_rank": 241
    },
    {
      "symbol": "CHZ",
      "name": "Chiliz",
      "id": "chiliz",
      "current_price": 0.0306,
      "price_change_percentage_24h": -4.51551,
      "market_cap_rank": 242
    },
    {
      "symbol": "XCN",
      "name": "Onyxcoin",
      "id": "chain-2",
      "current_price": 0.0085,
      "price_change_percentage_24h": -3.94044,
      "market_cap_rank": 243
    },
    {
      "symbol": "CCD",
      "name": "Concordium",
      "id": "concordium",
      "current_price": 0.0257,
      "price_change_percentage_24h": 9.79825,
      "market_cap_rank": 244
    },
    {
      "symbol": "SRUSD",
      "name": "Reservoir srUSD",
      "id": "reservoir-srusd",
      "current_price": 1.1056,
      "price_change_percentage_24h": 0.2034,
      "market_cap_rank": 245
    },
    {
      "symbol": "XEC",
      "name": "eCash",
      "id": "ecash",
      "current_price": 0,
      "price_change_percentage_24h": -1.26565,
      "market_cap_rank": 246
    },
    {
      "symbol": "RUNE",
      "name": "THORChain",
      "id": "thorchain",
      "current_price": 0.8423,
      "price_change_percentage_24h": -3.9597,
      "market_cap_rank": 247
    },
    {
      "symbol": "TOSHI",
      "name": "Toshi",
      "id": "toshi",
      "current_price": 0.0007,
      "price_change_percentage_24h": -5.39562,
      "market_cap_rank": 248
    }
  ]
}